{"source":"?????? ????? ??? ??","endpoint":"B552584/EvCharger/getChargerInfo","updatedAt":"2026-07-24T16:23:36+09:00","minimumOutputKw":350,"categoryRules":{"slow":"11kW ??","fast":"11kW ?? 200kW ??","ultraFast":"200kW ?? 350kW ??","hyperFast":"350kW ??"},"stationCount":234,"stations":[{"id":"PI320193","name":"BMW드라이빙센터 차징스테이션","address":"인천광역시 영종구 공항동로 136","lat":37.461350656,"lng":126.48522579,"power":400,"chargers":2,"totalChargers":76,"chargerCounts":{"slow":6,"fast":68,"ultraFast":0,"hyperFast":2},"operator":"GS차지비","useTime":"24시간 이용가능","parkingFree":"Y","kind":"H0","kindDetail":"H003"},{"id":"PI748400","name":"BMW차징허브라운지","address":"서울특별시 중구 퇴계로 15","lat":37.5570564,"lng":126.9745641,"power":400,"chargers":2,"totalChargers":6,"chargerCounts":{"slow":0,"fast":0,"ultraFast":4,"hyperFast":2},"operator":"GS차지비","useTime":"24시간 이용가능","parkingFree":"Y","kind":"G0","kindDetail":"G004"},{"id":"EO000010","name":"E1 광주금정 전기차 충전소","address":"전남광주통합특별시 광산구 북문대로 365","lat":35.19061524,"lng":126.8529116,"power":350,"chargers":1,"totalChargers":2,"chargerCounts":{"slow":0,"fast":0,"ultraFast":1,"hyperFast":1},"operator":"E1","useTime":"24시간 이용가능","parkingFree":"Y","kind":"E0","kindDetail":"E007"},{"id":"EO000309","name":"E1 용인처인휴게소(세종방향) 전기차충전소","address":"경기도 용인시 처인구 모현읍 곡현로619번길 36","lat":37.340893,"lng":127.21927,"power":350,"chargers":4,"totalChargers":18,"chargerCounts":{"slow":0,"fast":0,"ultraFast":14,"hyperFast":4},"operator":"E1","useTime":"24시간 이용가능","parkingFree":"Y","kind":"C0","kindDetail":"C001"},{"id":"EO000310","name":"E1 용인처인휴게소(포천방향) 전기차충전소","address":"경기도 용인시 처인구 모현읍 곡현로619번길 36","lat":37.340518,"lng":127.221019,"power":350,"chargers":4,"totalChargers":18,"chargerCounts":{"slow":0,"fast":0,"ultraFast":14,"hyperFast":4},"operator":"E1","useTime":"24시간 이용가능","parkingFree":"Y","kind":"C0","kindDetail":"C001"},{"id":"EO000012","name":"E1 의왕오렌지 전기차 충전소","address":"경기도 의왕시 경수대로 399","lat":37.3595293,"lng":126.9636701,"power":350,"chargers":2,"totalChargers":2,"chargerCounts":{"slow":0,"fast":0,"ultraFast":0,"hyperFast":2},"operator":"E1","useTime":"24시간 이용가능","parkingFree":"Y","kind":"E0","kindDetail":"E007"},{"id":"EO000013","name":"E1 익산 서해고속 전기차 충전소","address":"전북특별자치도 익산시 무왕로 801","lat":35.96487513,"lng":126.9478513,"power":350,"chargers":1,"totalChargers":2,"chargerCounts":{"slow":0,"fast":0,"ultraFast":1,"hyperFast":1},"operator":"E1","useTime":"24시간 이용가능","parkingFree":"Y","kind":"E0","kindDetail":"E007"},{"id":"EO000014","name":"E1 인천도림 전기차 충전소","address":"인천광역시 남동구 호구포로 388","lat":37.417091976,"lng":126.71536844,"power":350,"chargers":1,"totalChargers":2,"chargerCounts":{"slow":0,"fast":0,"ultraFast":1,"hyperFast":1},"operator":"E1","useTime":"24시간 이용가능","parkingFree":"Y","kind":"E0","kindDetail":"E007"},{"id":"EO000015","name":"E1 제주공항 전기차 충전소","address":"제주특별자치도 제주시 일주서로 7709","lat":33.494269176,"lng":126.47015032,"power":350,"chargers":1,"totalChargers":2,"chargerCounts":{"slow":0,"fast":0,"ultraFast":1,"hyperFast":1},"operator":"E1","useTime":"24시간 이용가능","parkingFree":"Y","kind":"E0","kindDetail":"E007"},{"id":"LI000301","name":"JS투어 충전소","address":"울산광역시 남구 상개로 202-11","lat":35.5027145,"lng":129.3184126,"power":400,"chargers":2,"totalChargers":2,"chargerCounts":{"slow":0,"fast":0,"ultraFast":0,"hyperFast":2},"operator":"엘에스이링크(주)","useTime":"비공용충전기(24시)","parkingFree":"Y","kind":"G0","kindDetail":"G004"},{"id":"ST601178","name":"SK에너지 박미주유소","address":"서울 금천구 시흥대로 39-7","lat":37.4372089,"lng":126.9024542,"power":350,"chargers":1,"totalChargers":2,"chargerCounts":{"slow":0,"fast":1,"ultraFast":0,"hyperFast":1},"operator":"SK일렉링크","useTime":"24시간 이용가능","parkingFree":"Y","kind":"E0","kindDetail":"E007"},{"id":"GS000009","name":"가든파이브주유소","address":"서울특별시 송파구 탄천동로 740","lat":37.476086,"lng":127.123543,"power":350,"chargers":1,"totalChargers":4,"chargerCounts":{"slow":0,"fast":0,"ultraFast":3,"hyperFast":1},"operator":"GS칼텍스","useTime":"24시간 이용가능","parkingFree":"Y","kind":"E0","kindDetail":"E007"},{"id":"CV004567","name":"거창휴게소(광주방향)","address":"경상남도 거창군 가조면 가조가야로 1543-81","lat":35.708378,"lng":128.0588178,"power":350,"chargers":1,"totalChargers":4,"chargerCounts":{"slow":0,"fast":1,"ultraFast":2,"hyperFast":1},"operator":"채비","useTime":"24시간 이용가능","parkingFree":"Y","kind":"C0","kindDetail":"C001"},{"id":"CV004561","name":"거창휴게소(대구방향)","address":"경상남도 거창군 가조면 가조가야로 1523","lat":35.706102,"lng":128.0575488,"power":350,"chargers":1,"totalChargers":4,"chargerCounts":{"slow":0,"fast":1,"ultraFast":2,"hyperFast":1},"operator":"채비","useTime":"24시간 이용가능","parkingFree":"Y","kind":"C0","kindDetail":"C001"},{"id":"CV004586","name":"경산휴게소(서울방향)","address":"경상북도 경산시 진량읍 대학로 1089","lat":35.8787862,"lng":128.8095519,"power":350,"chargers":2,"totalChargers":5,"chargerCounts":{"slow":0,"fast":0,"ultraFast":3,"hyperFast":2},"operator":"채비","useTime":"24시간 이용가능","parkingFree":"Y","kind":"C0","kindDetail":"C001"},{"id":"ST471319","name":"경주휴게소 (부산)","address":"경상북도 경주시 내남면 경부고속도로 59","lat":35.7260022,"lng":129.1944922,"power":350,"chargers":1,"totalChargers":4,"chargerCounts":{"slow":0,"fast":0,"ultraFast":3,"hyperFast":1},"operator":"SK일렉링크","useTime":"24시간 이용가능","parkingFree":"Y","kind":"C0","kindDetail":"C001"},{"id":"ST488205","name":"고성공룡나라휴게소 (대전)","address":"경상남도 고성군 대가면 통영대전고속도로 32","lat":35.0560099,"lng":128.2523501,"power":350,"chargers":1,"totalChargers":2,"chargerCounts":{"slow":0,"fast":0,"ultraFast":1,"hyperFast":1},"operator":"SK일렉링크","useTime":"24시간 이용가능","parkingFree":"Y","kind":"C0","kindDetail":"C001"},{"id":"ST488204","name":"고성공룡나라휴게소 (통영)","address":"경상남도 고성군 대가면 통영대전고속도로 29","lat":35.0519739,"lng":128.2634884,"power":350,"chargers":1,"totalChargers":3,"chargerCounts":{"slow":0,"fast":0,"ultraFast":2,"hyperFast":1},"operator":"SK일렉링크","useTime":"24시간 이용가능","parkingFree":"Y","kind":"C0","kindDetail":"C001"},{"id":"ME21A912","name":"고창고인돌(목포) 휴게소","address":"전북특별자치도 고창군 신림면 서해안고속도로 81","lat":35.4684345,"lng":126.6740667,"power":350,"chargers":2,"totalChargers":4,"chargerCounts":{"slow":0,"fast":2,"ultraFast":0,"hyperFast":2},"operator":"기후에너지환경부","useTime":"24시간 이용가능","parkingFree":"Y","kind":"C0","kindDetail":"C001"},{"id":"ST457902","name":"고창고인돌휴게소 (시흥)","address":"전북특별자치도 고창군 고창읍 서해안고속도로 80","lat":35.461230761,"lng":126.67176708,"power":350,"chargers":1,"totalChargers":2,"chargerCounts":{"slow":0,"fast":0,"ultraFast":1,"hyperFast":1},"operator":"SK일렉링크","useTime":"24시간 이용가능","parkingFree":"Y","kind":"C0","kindDetail":"C001"},{"id":"SGMAC024","name":"고창고인돌휴게소(서울)","address":"전북특별자치도 고창군 고창읍 서해안고속도로 80","lat":35.461201,"lng":126.67271,"power":350,"chargers":7,"totalChargers":8,"chargerCounts":{"slow":0,"fast":0,"ultraFast":1,"hyperFast":7},"operator":"SK시그넷","useTime":"24시간 이용가능","parkingFree":"Y","kind":"C0","kindDetail":"C001"},{"id":"SGMAC039","name":"곡성휴게소(순천)","address":"전남광주통합특별시 곡성군 겸면 호남고속도로 49","lat":35.25821,"lng":127.151332,"power":350,"chargers":2,"totalChargers":2,"chargerCounts":{"slow":0,"fast":0,"ultraFast":0,"hyperFast":2},"operator":"SK시그넷","useTime":"24시간 이용가능","parkingFree":"Y","kind":"C0","kindDetail":"C001"},{"id":"SGMAC040","name":"곡성휴게소(천안)","address":"전남광주통합특별시 곡성군 겸면 호남고속도로 50","lat":35.259579,"lng":127.152191,"power":350,"chargers":2,"totalChargers":2,"chargerCounts":{"slow":0,"fast":0,"ultraFast":0,"hyperFast":2},"operator":"SK시그넷","useTime":"24시간 이용가능","parkingFree":"Y","kind":"C0","kindDetail":"C001"},{"id":"ST441504","name":"공주휴게소 (대전)","address":"충청남도 공주시 당진영덕고속도로 72","lat":36.496864612,"lng":127.16690571,"power":350,"chargers":1,"totalChargers":3,"chargerCounts":{"slow":0,"fast":0,"ultraFast":2,"hyperFast":1},"operator":"SK일렉링크","useTime":"24시간 이용가능","parkingFree":"Y","kind":"C0","kindDetail":"C001"},{"id":"ST437604","name":"괴산휴게소 (창원)","address":"충청북도 괴산군 장연면 중부내륙고속도로 205","lat":36.831408768,"lng":127.95786572,"power":350,"chargers":1,"totalChargers":4,"chargerCounts":{"slow":0,"fast":0,"ultraFast":3,"hyperFast":1},"operator":"SK일렉링크","useTime":"24시간 이용가능","parkingFree":"Y","kind":"C0","kindDetail":"C001"},{"id":"SGMAC045","name":"군산휴게소(서울)","address":"전북특별자치도 군산시 나포면 서해안고속도로 148","lat":36.019243,"lng":126.797344,"power":350,"chargers":5,"totalChargers":5,"chargerCounts":{"slow":0,"fast":0,"ultraFast":0,"hyperFast":5},"operator":"SK시그넷","useTime":"24시간 이용가능","parkingFree":"Y","kind":"C0","kindDetail":"C001"},{"id":"ST477203","name":"군위휴게소 (부산)","address":"대구광역시 군위군 군위읍 경북대로 4084","lat":36.266553601,"lng":128.57503554,"power":350,"chargers":1,"totalChargers":3,"chargerCounts":{"slow":0,"fast":0,"ultraFast":2,"hyperFast":1},"operator":"SK일렉링크","useTime":"24시간 이용가능","parkingFree":"Y","kind":"C0","kindDetail":"C001"},{"id":"ME21A909","name":"금산인삼랜드(대전) 휴게소","address":"충청남도 금산군 군북면 대암길 34-30","lat":36.1547139,"lng":127.4973913,"power":350,"chargers":2,"totalChargers":4,"chargerCounts":{"slow":0,"fast":2,"ultraFast":0,"hyperFast":2},"operator":"기후에너지환경부","useTime":"24시간 이용가능","parkingFree":"Y","kind":"C0","kindDetail":"C001"},{"id":"ST601532","name":"금산인삼랜드휴게소 (대전)","address":"충청남도 금산군 군북면 대암길 34-30","lat":36.153856727,"lng":127.49787154,"power":350,"chargers":5,"totalChargers":6,"chargerCounts":{"slow":0,"fast":1,"ultraFast":0,"hyperFast":5},"operator":"SK일렉링크","useTime":"24시간 이용가능","parkingFree":"Y","kind":"C0","kindDetail":"C001"},{"id":"ST447102","name":"금산인삼랜드휴게소 (통영)","address":"충청남도 금산군 군북면 어필각로 300","lat":36.1545682,"lng":127.4952073,"power":350,"chargers":1,"totalChargers":4,"chargerCounts":{"slow":0,"fast":0,"ultraFast":3,"hyperFast":1},"operator":"SK일렉링크","useTime":"24시간 이용가능","parkingFree":"Y","kind":"C0","kindDetail":"C001"},{"id":"SGMAC035","name":"금산인삼랜드휴게소(통영)","address":"충청남도 금산군 군북면 어필각로 300","lat":36.153872,"lng":127.495242,"power":350,"chargers":7,"totalChargers":8,"chargerCounts":{"slow":0,"fast":0,"ultraFast":1,"hyperFast":7},"operator":"SK시그넷","useTime":"24시간 이용가능","parkingFree":"Y","kind":"C0","kindDetail":"C001"},{"id":"CV003164","name":"기흥조정경기장","address":"경기도 용인시 기흥구 동탄기흥로 923","lat":37.2415161,"lng":127.1020225,"power":350,"chargers":2,"totalChargers":4,"chargerCounts":{"slow":0,"fast":2,"ultraFast":0,"hyperFast":2},"operator":"채비","useTime":"24시간 이용가능","parkingFree":"N","kind":"J0","kindDetail":"J007"},{"id":"ST414634","name":"기흥휴게소 (부산)","address":"경기도 용인시 기흥구 공세로 173","lat":37.23573215,"lng":127.10355701,"power":350,"chargers":1,"totalChargers":8,"chargerCounts":{"slow":0,"fast":0,"ultraFast":7,"hyperFast":1},"operator":"SK일렉링크","useTime":"24시간 이용가능","parkingFree":"Y","kind":"C0","kindDetail":"C001"},{"id":"ST601540","name":"김제휴게소 (새만금)","address":"전북특별자치도 김제시 하정로 93","lat":35.841742,"lng":126.9038669,"power":350,"chargers":7,"totalChargers":8,"chargerCounts":{"slow":0,"fast":1,"ultraFast":0,"hyperFast":7},"operator":"SK일렉링크","useTime":"24시간 이용가능","parkingFree":"Y","kind":"C0","kindDetail":"C001"},{"id":"ST601541","name":"김제휴게소 (전주)","address":"전북특별자치도 김제시 백산면 하정2길 126","lat":35.8394016,"lng":126.8965202,"power":350,"chargers":6,"totalChargers":7,"chargerCounts":{"slow":0,"fast":1,"ultraFast":0,"hyperFast":6},"operator":"SK일렉링크","useTime":"24시간 이용가능","parkingFree":"Y","kind":"C0","kindDetail":"C001"},{"id":"CV004735","name":"김천휴게소(서울방향)","address":"경상북도 김천시 농소면 경부고속도로 194","lat":36.1307545,"lng":128.1632089,"power":350,"chargers":3,"totalChargers":5,"chargerCounts":{"slow":0,"fast":0,"ultraFast":2,"hyperFast":3},"operator":"채비","useTime":"24시간 이용가능","parkingFree":"Y","kind":"C0","kindDetail":"C001"},{"id":"ST482520","name":"김해금관가야휴게소 (창원)","address":"경상남도 김해시 대동면 동남로 400","lat":35.270339,"lng":129.003914,"power":350,"chargers":1,"totalChargers":2,"chargerCounts":{"slow":0,"fast":0,"ultraFast":1,"hyperFast":1},"operator":"SK일렉링크","useTime":"24시간 이용가능","parkingFree":"Y","kind":"C0","kindDetail":"C001"},{"id":"CV004575","name":"남성주참외휴게소(창원방향)","address":"경상북도 성주군 선남면 중부내륙고속도로 77","lat":35.8682504,"lng":128.3167949,"power":350,"chargers":2,"totalChargers":5,"chargerCounts":{"slow":0,"fast":0,"ultraFast":3,"hyperFast":2},"operator":"채비","useTime":"24시간 이용가능","parkingFree":"Y","kind":"C0","kindDetail":"C001"},{"id":"ST478401","name":"남성주휴게소 (양평)","address":"경상북도 성주군 용암면 중부내륙고속도로 76","lat":35.8573019,"lng":128.3199062,"power":350,"chargers":1,"totalChargers":2,"chargerCounts":{"slow":0,"fast":0,"ultraFast":1,"hyperFast":1},"operator":"SK일렉링크","useTime":"24시간 이용가능","parkingFree":"Y","kind":"C0","kindDetail":"C001"},{"id":"NH430002","name":"남청주농협 주유소","address":"충청북도 청주시 서원구 남이면 청남로 1234","lat":36.5605536,"lng":127.435845,"power":350,"chargers":1,"totalChargers":2,"chargerCounts":{"slow":0,"fast":0,"ultraFast":1,"hyperFast":1},"operator":"농협경제지주 신재생에너지센터","useTime":"24시간 이용가능","parkingFree":"Y","kind":"E0","kindDetail":"E007"},{"id":"ST428101","name":"내린천휴게소 (양양)","address":"강원특별자치도 인제군 상남면 서울양양고속도로 117-2","lat":37.9096305,"lng":128.2814753,"power":350,"chargers":1,"totalChargers":4,"chargerCounts":{"slow":0,"fast":0,"ultraFast":3,"hyperFast":1},"operator":"SK일렉링크","useTime":"24시간 이용가능","parkingFree":"Y","kind":"C0","kindDetail":"C001"},{"id":"ME21A910","name":"논공(광주) 휴게소","address":"대구광역시 달성군 논공읍 광주대구고속도로 169","lat":35.7672171,"lng":128.4034658,"power":350,"chargers":1,"totalChargers":3,"chargerCounts":{"slow":0,"fast":2,"ultraFast":0,"hyperFast":1},"operator":"기후에너지환경부","useTime":"24시간 이용가능","parkingFree":"Y","kind":"C0","kindDetail":"C001"},{"id":"ME21A903","name":"논공(대구) 휴게소","address":"대구광역시 달성군 논공읍 삼리리 538-2","lat":35.7649622,"lng":128.40266,"power":350,"chargers":2,"totalChargers":4,"chargerCounts":{"slow":0,"fast":2,"ultraFast":0,"hyperFast":2},"operator":"기후에너지환경부","useTime":"24시간 이용가능","parkingFree":"Y","kind":"C0","kindDetail":"C001"},{"id":"CV001768","name":"달성종합스포츠파크","address":"대구광역시 달성군 현풍읍 현풍동로 170","lat":35.701252,"lng":128.4425252,"power":350,"chargers":2,"totalChargers":9,"chargerCounts":{"slow":0,"fast":3,"ultraFast":4,"hyperFast":2},"operator":"채비","useTime":"24시간 이용가능","parkingFree":"Y","kind":"G0","kindDetail":"G004"},{"id":"ST421512","name":"대관령 강릉휴게소 (강릉)","address":"강원특별자치도 강릉시 성산면 영동고속도로 232","lat":37.7573566,"lng":128.8066236,"power":350,"chargers":1,"totalChargers":2,"chargerCounts":{"slow":0,"fast":0,"ultraFast":1,"hyperFast":1},"operator":"SK일렉링크","useTime":"24시간 이용가능","parkingFree":"Y","kind":"C0","kindDetail":"C001"},{"id":"ST421513","name":"대관령 강릉휴게소 (인천)","address":"강원특별자치도 강릉시 성산면 영동고속도로 231","lat":37.7586042,"lng":128.8045105,"power":350,"chargers":1,"totalChargers":2,"chargerCounts":{"slow":0,"fast":0,"ultraFast":1,"hyperFast":1},"operator":"SK일렉링크","useTime":"24시간 이용가능","parkingFree":"Y","kind":"C0","kindDetail":"C001"},{"id":"CV002390","name":"대구농수산물도매시장(농산)","address":"대구광역시 북구 매천로18길 34","lat":35.9018489,"lng":128.5417826,"power":350,"chargers":2,"totalChargers":2,"chargerCounts":{"slow":0,"fast":0,"ultraFast":0,"hyperFast":2},"operator":"채비","useTime":"24시간 이용가능","parkingFree":"N","kind":"E0","kindDetail":"E001"},{"id":"CV002389","name":"대구농수산물도매시장(수산)","address":"대구광역시 북구 매천로 63","lat":35.9019778,"lng":128.5409467,"power":350,"chargers":1,"totalChargers":1,"chargerCounts":{"slow":0,"fast":0,"ultraFast":0,"hyperFast":1},"operator":"채비","useTime":"24시간 이용가능","parkingFree":"N","kind":"E0","kindDetail":"E001"},{"id":"CV002351","name":"대구삼성라이온즈파크 달구벌주차장","address":"대구광역시 수성구 야구전설로 1","lat":35.8411906,"lng":128.6831342,"power":350,"chargers":2,"totalChargers":24,"chargerCounts":{"slow":19,"fast":3,"ultraFast":0,"hyperFast":2},"operator":"채비","useTime":"24시간 이용가능","parkingFree":"N","kind":"J0","kindDetail":"J007"},{"id":"CV002238","name":"대구수목원관리사무소 3주차장","address":"대구광역시 달서구 대곡동 1041","lat":35.8036342,"lng":128.519332,"power":350,"chargers":2,"totalChargers":5,"chargerCounts":{"slow":0,"fast":3,"ultraFast":0,"hyperFast":2},"operator":"채비","useTime":"24시간 이용가능","parkingFree":"Y","kind":"J0","kindDetail":"J006"},{"id":"CV002570","name":"대구시민운동장","address":"대구광역시 북구 고성로 191","lat":35.8816742,"lng":128.5892109,"power":350,"chargers":2,"totalChargers":4,"chargerCounts":{"slow":0,"fast":2,"ultraFast":0,"hyperFast":2},"operator":"채비","useTime":"24시간 이용가능","parkingFree":"Y","kind":"J0","kindDetail":"J007"},{"id":"ME21A913","name":"대천(목포) 휴게소","address":"충청남도 보령시 주교면 주교리 918-6","lat":36.3727068,"lng":126.556007,"power":350,"chargers":2,"totalChargers":4,"chargerCounts":{"slow":0,"fast":2,"ultraFast":0,"hyperFast":2},"operator":"기후에너지환경부","useTime":"24시간 이용가능","parkingFree":"Y","kind":"C0","kindDetail":"C001"},{"id":"ST457402","name":"덕유산휴게소 (통영)","address":"전북특별자치도 장수군 계북면 통영대전고속도로 147","lat":35.811823448,"lng":127.64363473,"power":350,"chargers":1,"totalChargers":3,"chargerCounts":{"slow":0,"fast":0,"ultraFast":2,"hyperFast":1},"operator":"SK일렉링크","useTime":"24시간 이용가능","parkingFree":"Y","kind":"C0","kindDetail":"C001"},{"id":"ST457303","name":"덕유산휴게소 (하남)","address":"전북특별자치도 무주군 안성면 통영대전고속도로 148","lat":35.815109793,"lng":127.64500481,"power":350,"chargers":1,"totalChargers":3,"chargerCounts":{"slow":0,"fast":0,"ultraFast":2,"hyperFast":1},"operator":"SK일렉링크","useTime":"24시간 이용가능","parkingFree":"Y","kind":"C0","kindDetail":"C001"},{"id":"SGMAC031","name":"덕유산휴게소(대전)","address":"전북특별자치도 무주군 안성면 통영대전고속도로 148","lat":35.816948,"lng":127.645962,"power":350,"chargers":6,"totalChargers":6,"chargerCounts":{"slow":0,"fast":0,"ultraFast":0,"hyperFast":6},"operator":"SK시그넷","useTime":"24시간 이용가능","parkingFree":"Y","kind":"C0","kindDetail":"C001"},{"id":"SGMAC019","name":"덕유산휴게소(통영)","address":"전북특별자치도 장수군 계북면 통영대전고속도로 147","lat":35.814258,"lng":127.643551,"power":350,"chargers":7,"totalChargers":7,"chargerCounts":{"slow":0,"fast":0,"ultraFast":0,"hyperFast":7},"operator":"SK시그넷","useTime":"24시간 이용가능","parkingFree":"Y","kind":"C0","kindDetail":"C001"},{"id":"ST478508","name":"동명휴게소 (춘천)","address":"경상북도 칠곡군 동명면 중앙고속도로 122","lat":36.0042538,"lng":128.5493454,"power":350,"chargers":1,"totalChargers":3,"chargerCounts":{"slow":0,"fast":0,"ultraFast":2,"hyperFast":1},"operator":"SK일렉링크","useTime":"24시간 이용가능","parkingFree":"Y","kind":"C0","kindDetail":"C001"},{"id":"CV001938","name":"동백사거리 공영주차장","address":"부산광역시 해운대구 마린시티1로 178","lat":36.1577396,"lng":129.1517411,"power":350,"chargers":2,"totalChargers":5,"chargerCounts":{"slow":0,"fast":3,"ultraFast":0,"hyperFast":2},"operator":"채비","useTime":"24시간 이용가능","parkingFree":"N","kind":"B0","kindDetail":"B001"},{"id":"LI000022","name":"동부 차고지","address":"경기 수원시 영통구 광교호수로 250","lat":37.2,"lng":127.0,"power":400,"chargers":10,"totalChargers":58,"chargerCounts":{"slow":0,"fast":2,"ultraFast":46,"hyperFast":10},"operator":"엘에스이링크","useTime":"24시간 이용가능","parkingFree":"Y","kind":"G0","kindDetail":"G004"},{"id":"LI000238","name":"동탄2차고지","address":"경기도 화성시 경기동로328번길 56","lat":37.1,"lng":127.1,"power":400,"chargers":28,"totalChargers":28,"chargerCounts":{"slow":0,"fast":0,"ultraFast":0,"hyperFast":28},"operator":"엘에스이링크","useTime":"24시간 이용가능","parkingFree":"Y","kind":"G0","kindDetail":"G004"},{"id":"PI747638","name":"메르세데스벤츠 HPC 분당 충전소","address":"경기도 성남시 분당구 대왕판교로 296","lat":37.3700398,"lng":127.1020091,"power":350,"chargers":6,"totalChargers":6,"chargerCounts":{"slow":0,"fast":0,"ultraFast":0,"hyperFast":6},"operator":"GS차지비","useTime":"24시간 이용가능","parkingFree":"N","kind":"B0","kindDetail":"B004"},{"id":"GS000032","name":"무수천주유소","address":"제주특별자치도 제주시 노형로 45","lat":33.463228,"lng":126.452021,"power":350,"chargers":2,"totalChargers":4,"chargerCounts":{"slow":0,"fast":0,"ultraFast":2,"hyperFast":2},"operator":"GS칼텍스","useTime":"24시간 이용가능","parkingFree":"Y","kind":"E0","kindDetail":"E007"},{"id":"ST421317","name":"문막휴게소 (인천)","address":"강원특별자치도 원주시 문막읍 개나루길 13","lat":37.297257541,"lng":127.81697022,"power":350,"chargers":1,"totalChargers":2,"chargerCounts":{"slow":0,"fast":0,"ultraFast":1,"hyperFast":1},"operator":"SK일렉링크","useTime":"24시간 이용가능","parkingFree":"Y","kind":"C0","kindDetail":"C001"},{"id":"CV004572","name":"문산휴게소(순천방향)","address":"경상남도 진주시 문산읍 남해고속도로 195","lat":35.1720577,"lng":128.1526988,"power":350,"chargers":1,"totalChargers":4,"chargerCounts":{"slow":0,"fast":0,"ultraFast":3,"hyperFast":1},"operator":"채비","useTime":"24시간 이용가능","parkingFree":"Y","kind":"C0","kindDetail":"C001"},{"id":"ST431148","name":"문의청남대휴게소 (영덕)","address":"충청북도 청주시 상당구 문의면 당진영덕고속도로 124","lat":36.5435254,"lng":127.4830365,"power":350,"chargers":1,"totalChargers":3,"chargerCounts":{"slow":0,"fast":0,"ultraFast":2,"hyperFast":1},"operator":"SK일렉링크","useTime":"24시간 이용가능","parkingFree":"Y","kind":"C0","kindDetail":"C001"},{"id":"ST431147","name":"문의청남대휴게소 (청주)","address":"충청북도 청주시 상당구 문의면 당진영덕고속도로 123","lat":36.5441999,"lng":127.4845484,"power":350,"chargers":1,"totalChargers":3,"chargerCounts":{"slow":0,"fast":0,"ultraFast":2,"hyperFast":1},"operator":"SK일렉링크","useTime":"24시간 이용가능","parkingFree":"Y","kind":"C0","kindDetail":"C001"},{"id":"SGMAC053","name":"밀양영남루휴게소(울산)","address":"경상남도 밀양시 무안면 함양울산고속도로 88","lat":35.4898129,"lng":128.6636083,"power":350,"chargers":7,"totalChargers":8,"chargerCounts":{"slow":0,"fast":0,"ultraFast":1,"hyperFast":7},"operator":"SK시그넷","useTime":"24시간 이용가능","parkingFree":"Y","kind":"C0","kindDetail":"C001"},{"id":"SGMAC054","name":"밀양영남루휴게소(함양)","address":"경상남도 밀양시 무안면 함양울산고속도로 87-1","lat":35.4920412,"lng":128.6642349,"power":350,"chargers":7,"totalChargers":8,"chargerCounts":{"slow":0,"fast":0,"ultraFast":1,"hyperFast":7},"operator":"SK시그넷","useTime":"24시간 이용가능","parkingFree":"Y","kind":"C0","kindDetail":"C001"},{"id":"SGMAC046","name":"백양사휴게소(순천)","address":"전남광주통합특별시 장성군 북이면 호남고속도로 107","lat":35.393946,"lng":126.80534,"power":350,"chargers":2,"totalChargers":2,"chargerCounts":{"slow":0,"fast":0,"ultraFast":0,"hyperFast":2},"operator":"SK시그넷","useTime":"24시간 이용가능","parkingFree":"Y","kind":"C0","kindDetail":"C001"},{"id":"SGMAC030","name":"백양사휴게소(천안)","address":"전남광주통합특별시 장성군 북일면 호남고속도로 108","lat":35.393644,"lng":126.807337,"power":350,"chargers":2,"totalChargers":2,"chargerCounts":{"slow":0,"fast":0,"ultraFast":0,"hyperFast":2},"operator":"SK시그넷","useTime":"24시간 이용가능","parkingFree":"Y","kind":"C0","kindDetail":"C001"},{"id":"ST601535","name":"벌곡휴게소 (논산)","address":"충청남도 논산시 벌곡면 호남지선고속도로 25","lat":36.218364744,"lng":127.27425755,"power":350,"chargers":3,"totalChargers":3,"chargerCounts":{"slow":0,"fast":0,"ultraFast":0,"hyperFast":3},"operator":"SK일렉링크","useTime":"24시간 이용가능","parkingFree":"Y","kind":"C0","kindDetail":"C001"},{"id":"ST413601","name":"별내휴게소","address":"경기도 남양주시 별내면 광전리 267-11","lat":37.691903,"lng":127.129855,"power":350,"chargers":1,"totalChargers":11,"chargerCounts":{"slow":0,"fast":8,"ultraFast":2,"hyperFast":1},"operator":"SK일렉링크","useTime":"24시간 이용가능","parkingFree":"Y","kind":"C0","kindDetail":"C001"},{"id":"SGMAC027","name":"보성녹차휴게소(순천)","address":"전남광주통합특별시 보성군 겸백면 남해고속도로 70","lat":34.807754,"lng":127.181635,"power":350,"chargers":2,"totalChargers":2,"chargerCounts":{"slow":0,"fast":0,"ultraFast":0,"hyperFast":2},"operator":"SK시그넷","useTime":"24시간 이용가능","parkingFree":"Y","kind":"C0","kindDetail":"C001"},{"id":"SGMAC034","name":"보성녹차휴게소(영암)","address":"전남광주통합특별시 보성군 미력면 남해고속도로 63","lat":34.814559,"lng":127.12519,"power":350,"chargers":2,"totalChargers":2,"chargerCounts":{"slow":0,"fast":0,"ultraFast":0,"hyperFast":2},"operator":"SK시그넷","useTime":"24시간 이용가능","parkingFree":"Y","kind":"C0","kindDetail":"C001"},{"id":"GS000024","name":"복지상일충전소","address":"서울특별시 강동구 천호대로 1452","lat":37.545097,"lng":127.169782,"power":350,"chargers":1,"totalChargers":2,"chargerCounts":{"slow":0,"fast":0,"ultraFast":1,"hyperFast":1},"operator":"GS칼텍스","useTime":"24시간 이용가능","parkingFree":"Y","kind":"E0","kindDetail":"E007"},{"id":"CV002279","name":"봉무공원제1주차장","address":"대구광역시 동구 봉무동 산 139","lat":35.9201417,"lng":128.6476393,"power":350,"chargers":1,"totalChargers":3,"chargerCounts":{"slow":0,"fast":2,"ultraFast":0,"hyperFast":1},"operator":"채비","useTime":"24시간 이용가능","parkingFree":"Y","kind":"B0","kindDetail":"B002"},{"id":"SGMAC037","name":"부안고려청자휴게소(목포)","address":"전북특별자치도 부안군 주산면 서해안고속도로 103","lat":35.671395,"lng":126.731858,"power":350,"chargers":6,"totalChargers":6,"chargerCounts":{"slow":0,"fast":0,"ultraFast":0,"hyperFast":6},"operator":"SK시그넷","useTime":"24시간 이용가능","parkingFree":"Y","kind":"C0","kindDetail":"C001"},{"id":"SGMAC038","name":"부안고려청자휴게소(서울)","address":"전북특별자치도 부안군 주산면 서해안고속도로 106","lat":35.672099,"lng":126.734838,"power":350,"chargers":6,"totalChargers":6,"chargerCounts":{"slow":0,"fast":0,"ultraFast":0,"hyperFast":6},"operator":"SK시그넷","useTime":"24시간 이용가능","parkingFree":"Y","kind":"C0","kindDetail":"C001"},{"id":"ST482408","name":"사천휴게소 (부산)","address":"경상남도 사천시 곤양면 서삼로 619","lat":35.07303422,"lng":128.01079619,"power":350,"chargers":1,"totalChargers":2,"chargerCounts":{"slow":0,"fast":0,"ultraFast":1,"hyperFast":1},"operator":"SK일렉링크","useTime":"24시간 이용가능","parkingFree":"Y","kind":"C0","kindDetail":"C001"},{"id":"ST482409","name":"사천휴게소 (순천)","address":"경상남도 사천시 곤양면 묵실길 31-11","lat":35.074905861,"lng":128.01292382,"power":350,"chargers":1,"totalChargers":2,"chargerCounts":{"slow":0,"fast":0,"ultraFast":1,"hyperFast":1},"operator":"SK일렉링크","useTime":"24시간 이용가능","parkingFree":"Y","kind":"C0","kindDetail":"C001"},{"id":"GS000022","name":"삼방주유소","address":"서울특별시 서초구 사평대로 364","lat":37.503764,"lng":127.023217,"power":350,"chargers":1,"totalChargers":4,"chargerCounts":{"slow":0,"fast":0,"ultraFast":3,"hyperFast":1},"operator":"GS칼텍스","useTime":"24시간 이용가능","parkingFree":"Y","kind":"E0","kindDetail":"E007"},{"id":"CV002151","name":"삼사해상공원","address":"경상북도 영덕군 강구면 해상공원길 65","lat":36.3491412,"lng":129.3849756,"power":350,"chargers":2,"totalChargers":5,"chargerCounts":{"slow":0,"fast":3,"ultraFast":0,"hyperFast":2},"operator":"채비","useTime":"24시간 이용가능","parkingFree":"Y","kind":"D0","kindDetail":"D001"},{"id":"LI000224","name":"상동차고지","address":"경기 부천시 원미구 상동 618","lat":37.4,"lng":126.7,"power":400,"chargers":5,"totalChargers":6,"chargerCounts":{"slow":0,"fast":1,"ultraFast":0,"hyperFast":5},"operator":"엘에스이링크","useTime":"24시간 이용가능","parkingFree":"Y","kind":"G0","kindDetail":"G004"},{"id":"ST442106","name":"서산휴게소 (목포)","address":"충청남도 서산시 해미면 서해안고속도로 241","lat":36.742905025,"lng":126.56502141,"power":350,"chargers":1,"totalChargers":2,"chargerCounts":{"slow":0,"fast":0,"ultraFast":1,"hyperFast":1},"operator":"SK일렉링크","useTime":"24시간 이용가능","parkingFree":"Y","kind":"C0","kindDetail":"C001"},{"id":"ST442107","name":"서산휴게소 (시흥)","address":"충청남도 서산시 해미면 서해안고속도로 242","lat":36.733948572,"lng":126.56492937,"power":350,"chargers":1,"totalChargers":2,"chargerCounts":{"slow":0,"fast":0,"ultraFast":1,"hyperFast":1},"operator":"SK일렉링크","useTime":"24시간 이용가능","parkingFree":"Y","kind":"C0","kindDetail":"C001"},{"id":"SGMAC047","name":"서산휴게소(서울)","address":"충청남도 서산시 해미면 서해안고속도로 242","lat":36.733994,"lng":126.567041,"power":350,"chargers":2,"totalChargers":3,"chargerCounts":{"slow":0,"fast":0,"ultraFast":1,"hyperFast":2},"operator":"SK시그넷","useTime":"24시간 이용가능","parkingFree":"Y","kind":"C0","kindDetail":"C001"},{"id":"ST601528","name":"서여주휴게소 (양평)","address":"경기도 여주시 세종대왕면 중부내륙고속도로 272","lat":37.279323722,"lng":127.5803265,"power":350,"chargers":2,"totalChargers":3,"chargerCounts":{"slow":0,"fast":1,"ultraFast":0,"hyperFast":2},"operator":"SK일렉링크","useTime":"24시간 이용가능","parkingFree":"Y","kind":"C0","kindDetail":"C001"},{"id":"ST116534","name":"서울만남휴게소 (부산)","address":"서울특별시 서초구 양재대로12길 73-71","lat":37.45958384,"lng":127.04233054,"power":350,"chargers":1,"totalChargers":3,"chargerCounts":{"slow":0,"fast":0,"ultraFast":2,"hyperFast":1},"operator":"SK일렉링크","useTime":"24시간 이용가능","parkingFree":"Y","kind":"C0","kindDetail":"C001"},{"id":"ST447703","name":"서천휴게소 (목포)","address":"충청남도 서천군 비인면 성산리 416-1","lat":36.1295536,"lng":126.626455,"power":350,"chargers":1,"totalChargers":2,"chargerCounts":{"slow":0,"fast":0,"ultraFast":1,"hyperFast":1},"operator":"SK일렉링크","useTime":"24시간 이용가능","parkingFree":"Y","kind":"C0","kindDetail":"C001"},{"id":"ST601536","name":"서천휴게소 (서울)","address":"충청남도 서천군 비인면 서해안고속도로 168","lat":36.131318774,"lng":126.62819595,"power":350,"chargers":6,"totalChargers":6,"chargerCounts":{"slow":0,"fast":0,"ultraFast":0,"hyperFast":6},"operator":"SK일렉링크","useTime":"24시간 이용가능","parkingFree":"Y","kind":"C0","kindDetail":"C001"},{"id":"SGMAC048","name":"서천휴게소(목포)","address":"충청남도 서천군 비인면 서해안고속도로 169","lat":36.130116,"lng":126.625933,"power":350,"chargers":5,"totalChargers":6,"chargerCounts":{"slow":0,"fast":0,"ultraFast":1,"hyperFast":5},"operator":"SK시그넷","useTime":"24시간 이용가능","parkingFree":"Y","kind":"C0","kindDetail":"C001"},{"id":"LI000321","name":"선광신컨테이너터미널(SNCT)","address":"인천광역시 연수구 인천신항대로 707","lat":37.34713,"lng":126.63444,"power":360,"chargers":1,"totalChargers":15,"chargerCounts":{"slow":0,"fast":1,"ultraFast":13,"hyperFast":1},"operator":"엘에스이링크(주)","useTime":"24시간 이용가능","parkingFree":"Y","kind":"G0","kindDetail":"G004"},{"id":"ST471927","name":"선산휴게소 (양평)","address":"경상북도 구미시 옥성면 중부내륙고속도로 128","lat":36.27651642,"lng":128.2497795,"power":350,"chargers":1,"totalChargers":4,"chargerCounts":{"slow":0,"fast":0,"ultraFast":3,"hyperFast":1},"operator":"SK일렉링크","useTime":"24시간 이용가능","parkingFree":"Y","kind":"C0","kindDetail":"C001"},{"id":"SGMAC049","name":"섬진강휴게소(부산)","address":"전남광주통합특별시 광양시 진월면 섬진강매화로 141","lat":34.985022,"lng":127.771344,"power":350,"chargers":4,"totalChargers":4,"chargerCounts":{"slow":0,"fast":0,"ultraFast":0,"hyperFast":4},"operator":"SK시그넷","useTime":"24시간 이용가능","parkingFree":"Y","kind":"C0","kindDetail":"C001"},{"id":"SGMAC055","name":"섬진강휴게소(순천)","address":"전남광주통합특별시 광양시 진월면 신답길 24-14","lat":34.98513624,"lng":127.7684389,"power":350,"chargers":7,"totalChargers":7,"chargerCounts":{"slow":0,"fast":0,"ultraFast":0,"hyperFast":7},"operator":"SK시그넷","useTime":"24시간 이용가능","parkingFree":"Y","kind":"C0","kindDetail":"C001"},{"id":"ME21A911","name":"성주(양평) 휴게소","address":"경상북도 성주군 초전면 중부내륙고속도로 98","lat":36.0076887,"lng":128.2609428,"power":350,"chargers":2,"totalChargers":4,"chargerCounts":{"slow":0,"fast":2,"ultraFast":0,"hyperFast":2},"operator":"기후에너지환경부","useTime":"24시간 이용가능","parkingFree":"Y","kind":"C0","kindDetail":"C001"},{"id":"CV004564","name":"성주휴게소(양평방향)","address":"경상북도 성주군 초전면 중부내륙고속도로 98","lat":36.00761676,"lng":128.2609592,"power":350,"chargers":2,"totalChargers":5,"chargerCounts":{"slow":0,"fast":0,"ultraFast":3,"hyperFast":2},"operator":"채비","useTime":"24시간 이용가능","parkingFree":"Y","kind":"C0","kindDetail":"C001"},{"id":"CV000886","name":"세종 조치원중학교","address":"세종특별자치시 조치원읍 조치원중고길 10-1","lat":36.612186,"lng":127.299713,"power":350,"chargers":2,"totalChargers":2,"chargerCounts":{"slow":0,"fast":0,"ultraFast":0,"hyperFast":2},"operator":"채비","useTime":"09:00~18:00","parkingFree":"Y","kind":"J0","kindDetail":"J001"},{"id":"ME21A915","name":"속리산(청주) 휴게소","address":"충청북도 보은군 마로면 적암리 182-7","lat":36.4469821,"lng":127.8691518,"power":350,"chargers":2,"totalChargers":4,"chargerCounts":{"slow":0,"fast":2,"ultraFast":0,"hyperFast":2},"operator":"기후에너지환경부","useTime":"24시간 이용가능","parkingFree":"Y","kind":"C0","kindDetail":"C001"},{"id":"CV004280","name":"수동휴게소(포천방향)","address":"경기도 남양주시 수동면 비룡로 1183","lat":37.7337305,"lng":127.291269,"power":350,"chargers":2,"totalChargers":8,"chargerCounts":{"slow":0,"fast":0,"ultraFast":6,"hyperFast":2},"operator":"채비","useTime":"24시간 이용가능","parkingFree":"Y","kind":"C0","kindDetail":"C001"},{"id":"CV004279","name":"수동휴게소(화도방향)","address":"경기도 남양주시 수동면 비룡로 1183-1","lat":37.727501,"lng":127.292203,"power":350,"chargers":2,"totalChargers":8,"chargerCounts":{"slow":0,"fast":0,"ultraFast":6,"hyperFast":2},"operator":"채비","useTime":"24시간 이용가능","parkingFree":"Y","kind":"C0","kindDetail":"C001"},{"id":"SGMAC042","name":"순천휴게소(순천)","address":"전남광주통합특별시 순천시 서면 호남고속도로 3","lat":35.008641,"lng":127.445401,"power":350,"chargers":2,"totalChargers":3,"chargerCounts":{"slow":0,"fast":0,"ultraFast":1,"hyperFast":2},"operator":"SK시그넷","useTime":"24시간 이용가능","parkingFree":"Y","kind":"C0","kindDetail":"C001"},{"id":"GS000174","name":"스마트플러스허브(제주)","address":"제주특별자치도 제주시 공항로 32","lat":33.5042318,"lng":126.4951907,"power":350,"chargers":2,"totalChargers":6,"chargerCounts":{"slow":0,"fast":0,"ultraFast":4,"hyperFast":2},"operator":"GS칼텍스","useTime":"24시간 이용가능","parkingFree":"Y","kind":"E0","kindDetail":"E007"},{"id":"GS000116","name":"신제주로터리 1","address":"제주특별자치도 제주시 연동 301","lat":33.490404,"lng":126.496546,"power":350,"chargers":2,"totalChargers":4,"chargerCounts":{"slow":0,"fast":0,"ultraFast":2,"hyperFast":2},"operator":"GS칼텍스","useTime":"24시간 이용가능","parkingFree":"Y","kind":"G0","kindDetail":"G004"},{"id":"KL200220","name":"신창휴게소","address":"충청남도 아산시 신창면 온천대로 725","lat":36.768470985,"lng":126.92538376,"power":400,"chargers":3,"totalChargers":3,"chargerCounts":{"slow":0,"fast":0,"ultraFast":0,"hyperFast":3},"operator":"(주)클린일렉스","useTime":"24시간 이용가능","parkingFree":"Y","kind":"G0","kindDetail":"G004"},{"id":"ME21A906","name":"신탄진(서울) 휴게소","address":"대전광역시 대덕구 상서동 373-21","lat":36.4267118,"lng":127.4181826,"power":350,"chargers":2,"totalChargers":4,"chargerCounts":{"slow":0,"fast":2,"ultraFast":0,"hyperFast":2},"operator":"기후에너지환경부","useTime":"24시간 이용가능","parkingFree":"Y","kind":"C0","kindDetail":"C001"},{"id":"ST302307","name":"신탄진휴게소 (서울)","address":"대전광역시 대덕구 산업단지로 27","lat":36.428490523,"lng":127.41785136,"power":350,"chargers":1,"totalChargers":3,"chargerCounts":{"slow":0,"fast":0,"ultraFast":2,"hyperFast":1},"operator":"SK일렉링크","useTime":"24시간 이용가능","parkingFree":"Y","kind":"C0","kindDetail":"C001"},{"id":"LI000027","name":"안녕동 차고지","address":"경기도 화성시 안녕길 49","lat":37.2,"lng":126.9,"power":400,"chargers":37,"totalChargers":38,"chargerCounts":{"slow":0,"fast":1,"ultraFast":0,"hyperFast":37},"operator":"엘에스이링크","useTime":"24시간 이용가능","parkingFree":"Y","kind":"G0","kindDetail":"G004"},{"id":"ME21A905","name":"안성맞춤(평택) 휴게소","address":"경기도 안성시 서운면 평택제천고속도로 41","lat":36.9696449,"lng":127.2745799,"power":350,"chargers":2,"totalChargers":4,"chargerCounts":{"slow":0,"fast":2,"ultraFast":0,"hyperFast":2},"operator":"기후에너지환경부","useTime":"24시간 이용가능","parkingFree":"Y","kind":"C0","kindDetail":"C001"},{"id":"CV002128","name":"안심공영주차장","address":"대구광역시 동구 괴전동 401-2","lat":35.8688091,"lng":128.7349969,"power":350,"chargers":2,"totalChargers":6,"chargerCounts":{"slow":0,"fast":4,"ultraFast":0,"hyperFast":2},"operator":"채비","useTime":"24시간 이용가능","parkingFree":"N","kind":"B0","kindDetail":"B001"},{"id":"EC310001","name":"언양(서울)휴게소 (급)","address":"울산광역시 울주군 언양읍 경부고속도로 44","lat":35.598372726,"lng":129.1409269,"power":360,"chargers":4,"totalChargers":4,"chargerCounts":{"slow":0,"fast":0,"ultraFast":0,"hyperFast":4},"operator":"이지차저","useTime":"24시간 이용가능","parkingFree":"Y","kind":"C0","kindDetail":"C001"},{"id":"ST317115","name":"언양휴게소 (서울)","address":"울산광역시 울주군 언양읍 경부고속도로 44","lat":35.598372726,"lng":129.1409269,"power":350,"chargers":1,"totalChargers":4,"chargerCounts":{"slow":0,"fast":0,"ultraFast":3,"hyperFast":1},"operator":"SK일렉링크","useTime":"24시간 이용가능","parkingFree":"Y","kind":"C0","kindDetail":"C001"},{"id":"CV001221","name":"엑스코 제2전시장","address":"대구광역시 북구 유통단지로 110","lat":35.908024,"lng":128.614576,"power":350,"chargers":2,"totalChargers":10,"chargerCounts":{"slow":3,"fast":5,"ultraFast":0,"hyperFast":2},"operator":"채비","useTime":"09:00~18:00","parkingFree":"N","kind":"D0","kindDetail":"D002"},{"id":"ST451403","name":"여산휴게소 (순천)","address":"전북특별자치도 익산시 여산면 호남고속도로 191","lat":36.048993949,"lng":127.10258161,"power":350,"chargers":1,"totalChargers":4,"chargerCounts":{"slow":0,"fast":0,"ultraFast":3,"hyperFast":1},"operator":"SK일렉링크","useTime":"24시간 이용가능","parkingFree":"Y","kind":"C0","kindDetail":"C001"},{"id":"ST416712","name":"여주휴게소 (강릉)","address":"경기도 여주시 가남읍 여주남로 722","lat":37.2384762,"lng":127.5717979,"power":350,"chargers":1,"totalChargers":6,"chargerCounts":{"slow":0,"fast":0,"ultraFast":5,"hyperFast":1},"operator":"SK일렉링크","useTime":"24시간 이용가능","parkingFree":"Y","kind":"C0","kindDetail":"C001"},{"id":"ST416713","name":"여주휴게소 (인천)","address":"경기도 여주시 가남읍 화평길 116","lat":37.2398643,"lng":127.5706438,"power":350,"chargers":1,"totalChargers":4,"chargerCounts":{"slow":0,"fast":0,"ultraFast":3,"hyperFast":1},"operator":"SK일렉링크","useTime":"24시간 이용가능","parkingFree":"Y","kind":"C0","kindDetail":"C001"},{"id":"CV002164","name":"영덕해파랑공원","address":"경상북도 영덕군 강구면 강구리 584","lat":36.3608047,"lng":129.3925334,"power":350,"chargers":2,"totalChargers":5,"chargerCounts":{"slow":0,"fast":3,"ultraFast":0,"hyperFast":2},"operator":"채비","useTime":"24시간 이용가능","parkingFree":"Y","kind":"D0","kindDetail":"D001"},{"id":"ST487404","name":"영산 휴게소 (창원)","address":"경상남도 창녕군 영산면 장척호수길 56-110","lat":35.429177987,"lng":128.49534835,"power":350,"chargers":1,"totalChargers":3,"chargerCounts":{"slow":0,"fast":0,"ultraFast":2,"hyperFast":1},"operator":"SK일렉링크","useTime":"24시간 이용가능","parkingFree":"Y","kind":"C0","kindDetail":"C001"},{"id":"ST472307","name":"영천휴게소 (대구)","address":"경상북도 영천시 임고면 운주로 791","lat":36.05268055,"lng":129.04497684,"power":350,"chargers":1,"totalChargers":6,"chargerCounts":{"slow":0,"fast":0,"ultraFast":5,"hyperFast":1},"operator":"SK일렉링크","useTime":"24시간 이용가능","parkingFree":"Y","kind":"C0","kindDetail":"C001"},{"id":"CV004734","name":"영천휴게소(포항방향)","address":"경상북도 영천시 임고면 운주로 777","lat":36.0519821,"lng":129.0411471,"power":350,"chargers":2,"totalChargers":5,"chargerCounts":{"slow":0,"fast":0,"ultraFast":3,"hyperFast":2},"operator":"채비","useTime":"24시간 이용가능","parkingFree":"Y","kind":"C0","kindDetail":"C001"},{"id":"ME21A904","name":"예산(대전) 휴게소","address":"충청남도 예산군 대흥면 탄방리 136","lat":36.6243077,"lng":126.8395678,"power":350,"chargers":2,"totalChargers":4,"chargerCounts":{"slow":0,"fast":2,"ultraFast":0,"hyperFast":2},"operator":"기후에너지환경부","useTime":"24시간 이용가능","parkingFree":"Y","kind":"C0","kindDetail":"C001"},{"id":"ST457502","name":"오수휴게소 (순천)","address":"전북특별자치도 임실군 오수면 순천완주고속도로 73","lat":35.5410082,"lng":127.309392,"power":350,"chargers":1,"totalChargers":4,"chargerCounts":{"slow":0,"fast":0,"ultraFast":3,"hyperFast":1},"operator":"SK일렉링크","useTime":"24시간 이용가능","parkingFree":"Y","kind":"C0","kindDetail":"C001"},{"id":"ST457503","name":"오수휴게소 (완주)","address":"전북특별자치도 임실군 오수면 순천완주고속도로 74","lat":35.5402456,"lng":127.3116152,"power":350,"chargers":1,"totalChargers":4,"chargerCounts":{"slow":0,"fast":0,"ultraFast":3,"hyperFast":1},"operator":"SK일렉링크","useTime":"24시간 이용가능","parkingFree":"N","kind":"C0","kindDetail":"C001"},{"id":"SGMAC018","name":"오수휴게소(순천)","address":"전북특별자치도 임실군 오수면 순천완주고속도로 73","lat":35.540296,"lng":127.30934,"power":350,"chargers":7,"totalChargers":8,"chargerCounts":{"slow":0,"fast":0,"ultraFast":1,"hyperFast":7},"operator":"SK시그넷","useTime":"24시간 이용가능","parkingFree":"Y","kind":"C0","kindDetail":"C001"},{"id":"SGMAC016","name":"오수휴게소(완주)","address":"전북특별자치도 임실군 오수면 순천완주고속도로 74","lat":35.539353,"lng":127.311175,"power":350,"chargers":2,"totalChargers":2,"chargerCounts":{"slow":0,"fast":0,"ultraFast":0,"hyperFast":2},"operator":"SK시그넷","useTime":"24시간 이용가능","parkingFree":"Y","kind":"C0","kindDetail":"C001"},{"id":"ST431149","name":"오창휴게소 (하남)","address":"충청북도 청주시 청원구 오창읍 중부고속도로 20","lat":36.756596962,"lng":127.48219971,"power":350,"chargers":1,"totalChargers":4,"chargerCounts":{"slow":0,"fast":0,"ultraFast":3,"hyperFast":1},"operator":"SK일렉링크","useTime":"24시간 이용가능","parkingFree":"Y","kind":"C0","kindDetail":"C001"},{"id":"ST421511","name":"옥계휴게소 (속초)","address":"강원특별자치도 강릉시 옥계면 동해고속도로 320","lat":37.616167236,"lng":129.06011403,"power":350,"chargers":1,"totalChargers":2,"chargerCounts":{"slow":0,"fast":0,"ultraFast":1,"hyperFast":1},"operator":"SK일렉링크","useTime":"24시간 이용가능","parkingFree":"Y","kind":"C0","kindDetail":"C001"},{"id":"SGMAC017","name":"옥천휴게소(부산)","address":"충청북도 옥천군 옥천읍 서대구일로 265-19","lat":36.296571,"lng":127.596369,"power":350,"chargers":7,"totalChargers":7,"chargerCounts":{"slow":0,"fast":0,"ultraFast":0,"hyperFast":7},"operator":"SK시그넷","useTime":"24시간 이용가능","parkingFree":"Y","kind":"C0","kindDetail":"C001"},{"id":"SGMAC028","name":"옥천휴게소(서울)","address":"충청북도 옥천군 옥천읍 옥천동이로 242-34","lat":36.2979263,"lng":127.599073,"power":350,"chargers":7,"totalChargers":7,"chargerCounts":{"slow":0,"fast":0,"ultraFast":0,"hyperFast":7},"operator":"SK시그넷","useTime":"24시간 이용가능","parkingFree":"Y","kind":"C0","kindDetail":"C001"},{"id":"CV004581","name":"와촌휴게소(포항방향)","address":"경상북도 경산시 와촌면 강학리 산71-1","lat":35.9519462,"lng":128.7744631,"power":350,"chargers":2,"totalChargers":5,"chargerCounts":{"slow":0,"fast":0,"ultraFast":3,"hyperFast":2},"operator":"채비","useTime":"24시간 이용가능","parkingFree":"Y","kind":"C0","kindDetail":"C001"},{"id":"CV002163","name":"외환들공영주차장","address":"대구광역시 수성구 미술관로 40-1","lat":35.828936495,"lng":128.6741066,"power":350,"chargers":2,"totalChargers":8,"chargerCounts":{"slow":0,"fast":6,"ultraFast":0,"hyperFast":2},"operator":"채비","useTime":"24시간 이용가능","parkingFree":"N","kind":"B0","kindDetail":"B001"},{"id":"ME22M301","name":"용산 전쟁기념관 소형 주차장","address":"서울특별시 용산구 이태원로 29","lat":37.5373,"lng":126.9752,"power":350,"chargers":4,"totalChargers":6,"chargerCounts":{"slow":0,"fast":2,"ultraFast":0,"hyperFast":4},"operator":"기후에너지환경부","useTime":"24시간 이용가능","parkingFree":"Y","kind":"J0","kindDetail":"J005"},{"id":"CV003152","name":"용인시청","address":"경기도 용인시 처인구 중부대로 1199","lat":37.241182,"lng":127.1783502,"power":350,"chargers":2,"totalChargers":6,"chargerCounts":{"slow":0,"fast":4,"ultraFast":0,"hyperFast":2},"operator":"채비","useTime":"09:00~18:00","parkingFree":"N","kind":"A0","kindDetail":"A003"},{"id":"ST317117","name":"울주휴게소 (울산)","address":"울산광역시 울주군 삼동면 함양울산고속도로 134","lat":35.51155062,"lng":129.1321585,"power":350,"chargers":1,"totalChargers":4,"chargerCounts":{"slow":0,"fast":0,"ultraFast":3,"hyperFast":1},"operator":"SK일렉링크","useTime":"24시간 이용가능","parkingFree":"Y","kind":"C0","kindDetail":"C001"},{"id":"ST317116","name":"울주휴게소 (함양)","address":"울산광역시 울주군 삼동면 함양울산고속도로 133","lat":35.511856806,"lng":129.12972887,"power":350,"chargers":1,"totalChargers":3,"chargerCounts":{"slow":0,"fast":0,"ultraFast":2,"hyperFast":1},"operator":"SK일렉링크","useTime":"24시간 이용가능","parkingFree":"Y","kind":"C0","kindDetail":"C001"},{"id":"BE241206","name":"워터 강릉대관령휴게소 강릉방향","address":"강원특별자치도 강릉시 성산면 영동고속도로 232","lat":37.7579034,"lng":128.8070992,"power":350,"chargers":6,"totalChargers":7,"chargerCounts":{"slow":0,"fast":0,"ultraFast":1,"hyperFast":6},"operator":"브라이트에너지파트너스","useTime":"24시간 이용가능","parkingFree":"Y","kind":"C0","kindDetail":"C001"},{"id":"BE241207","name":"워터 강릉대관령휴게소 인천방향","address":"강원특별자치도 강릉시 성산면 영동고속도로 231","lat":37.7592114,"lng":128.8046893,"power":350,"chargers":6,"totalChargers":7,"chargerCounts":{"slow":0,"fast":0,"ultraFast":1,"hyperFast":6},"operator":"브라이트에너지파트너스","useTime":"24시간 이용가능","parkingFree":"Y","kind":"C0","kindDetail":"C001"},{"id":"BE241237","name":"워터 경주휴게소 부산방향","address":"경상북도 경주시 내남면 경부고속도로 59","lat":35.724529,"lng":129.192708,"power":350,"chargers":4,"totalChargers":5,"chargerCounts":{"slow":0,"fast":0,"ultraFast":1,"hyperFast":4},"operator":"브라이트에너지파트너스","useTime":"24시간 이용가능","parkingFree":"Y","kind":"C0","kindDetail":"C001"},{"id":"BE241238","name":"워터 고성공룡나라휴게소 대전방향","address":"경상남도 고성군 대가면 통영대전고속도로 32","lat":35.055977,"lng":128.253486,"power":350,"chargers":5,"totalChargers":6,"chargerCounts":{"slow":0,"fast":0,"ultraFast":1,"hyperFast":5},"operator":"브라이트에너지파트너스","useTime":"24시간 이용가능","parkingFree":"Y","kind":"C0","kindDetail":"C001"},{"id":"BE241239","name":"워터 고성공룡나라휴게소 통영방향","address":"경상남도 고성군 대가면 통영대전고속도로 29","lat":35.051847,"lng":128.263186,"power":350,"chargers":4,"totalChargers":5,"chargerCounts":{"slow":0,"fast":0,"ultraFast":1,"hyperFast":4},"operator":"브라이트에너지파트너스","useTime":"24시간 이용가능","parkingFree":"Y","kind":"C0","kindDetail":"C001"},{"id":"BE241223","name":"워터 괴산휴게소 창원방향","address":"충청북도 괴산군 장연면 중부내륙고속도로 205","lat":36.8309538,"lng":127.9578331,"power":350,"chargers":7,"totalChargers":8,"chargerCounts":{"slow":0,"fast":0,"ultraFast":1,"hyperFast":7},"operator":"브라이트에너지파트너스","useTime":"24시간 이용가능","parkingFree":"Y","kind":"C0","kindDetail":"C001"},{"id":"BE241230","name":"워터 군위휴게소 부산방향","address":"대구광역시 군위군 군위읍 경북대로 4084","lat":36.2661344,"lng":128.5749656,"power":350,"chargers":1,"totalChargers":2,"chargerCounts":{"slow":0,"fast":0,"ultraFast":1,"hyperFast":1},"operator":"브라이트에너지파트너스","useTime":"24시간 이용가능","parkingFree":"Y","kind":"C0","kindDetail":"C001"},{"id":"BE241231","name":"워터 남성주참외휴게소 양평방향","address":"경상북도 성주군 용암면 중부내륙고속도로 76","lat":35.8570205,"lng":128.3199785,"power":350,"chargers":2,"totalChargers":3,"chargerCounts":{"slow":0,"fast":0,"ultraFast":1,"hyperFast":2},"operator":"브라이트에너지파트너스","useTime":"24시간 이용가능","parkingFree":"Y","kind":"C0","kindDetail":"C001"},{"id":"BE241208","name":"워터 내린천휴게소 서울방향","address":"강원특별자치도 인제군 상남면 서울양양고속도로 117","lat":37.9164991,"lng":128.2864823,"power":350,"chargers":3,"totalChargers":5,"chargerCounts":{"slow":0,"fast":0,"ultraFast":2,"hyperFast":3},"operator":"브라이트에너지파트너스","useTime":"24시간 이용가능","parkingFree":"Y","kind":"C0","kindDetail":"C001"},{"id":"BE241209","name":"워터 내린천휴게소 양양방향","address":"강원특별자치도 인제군 상남면 서울양양고속도로 117","lat":37.915306,"lng":128.2880736,"power":350,"chargers":7,"totalChargers":8,"chargerCounts":{"slow":0,"fast":0,"ultraFast":1,"hyperFast":7},"operator":"브라이트에너지파트너스","useTime":"24시간 이용가능","parkingFree":"Y","kind":"C0","kindDetail":"C001"},{"id":"BE241224","name":"워터 문경휴게소 양평방향","address":"경상북도 문경시 중부내륙고속도로 174","lat":36.6197881,"lng":128.1528585,"power":350,"chargers":5,"totalChargers":6,"chargerCounts":{"slow":0,"fast":0,"ultraFast":1,"hyperFast":5},"operator":"브라이트에너지파트너스","useTime":"24시간 이용가능","parkingFree":"Y","kind":"C0","kindDetail":"C001"},{"id":"BE241225","name":"워터 문경휴게소 창원방향","address":"경상북도 문경시 중부내륙고속도로 173","lat":36.6205741,"lng":128.1499415,"power":350,"chargers":3,"totalChargers":4,"chargerCounts":{"slow":0,"fast":0,"ultraFast":1,"hyperFast":3},"operator":"브라이트에너지파트너스","useTime":"24시간 이용가능","parkingFree":"Y","kind":"C0","kindDetail":"C001"},{"id":"BE241210","name":"워터 문막휴게소 인천방향","address":"강원특별자치도 원주시 문막읍 개나루길 13","lat":37.297427,"lng":127.8173209,"power":350,"chargers":5,"totalChargers":6,"chargerCounts":{"slow":0,"fast":0,"ultraFast":1,"hyperFast":5},"operator":"브라이트에너지파트너스","useTime":"24시간 이용가능","parkingFree":"Y","kind":"C0","kindDetail":"C001"},{"id":"BE241243","name":"워터 산청휴게소 통영방향","address":"경상남도 산청군 단성면 통영대전고속도로 77","lat":35.3344392,"lng":127.9371415,"power":350,"chargers":3,"totalChargers":4,"chargerCounts":{"slow":0,"fast":0,"ultraFast":1,"hyperFast":3},"operator":"브라이트에너지파트너스","useTime":"24시간 이용가능","parkingFree":"Y","kind":"C0","kindDetail":"C001"},{"id":"BE241211","name":"워터 서여주휴게소 창원방향","address":"경기도 여주시 세종대왕면 중부내륙고속도로 271","lat":37.2789844,"lng":127.5783541,"power":350,"chargers":3,"totalChargers":4,"chargerCounts":{"slow":0,"fast":0,"ultraFast":1,"hyperFast":3},"operator":"브라이트에너지파트너스","useTime":"24시간 이용가능","parkingFree":"Y","kind":"C0","kindDetail":"C001"},{"id":"BE241232","name":"워터 안동휴게소 부산방향","address":"경상북도 안동시 풍산읍 풍산태사로 1903-27","lat":36.5529764,"lng":128.6423763,"power":350,"chargers":3,"totalChargers":4,"chargerCounts":{"slow":0,"fast":0,"ultraFast":1,"hyperFast":3},"operator":"브라이트에너지파트너스","useTime":"24시간 이용가능","parkingFree":"Y","kind":"C0","kindDetail":"C001"},{"id":"BE241212","name":"워터 여주휴게소 강릉방향","address":"경기도 여주시 가남읍 여주남로 722","lat":37.2380912,"lng":127.5702879,"power":350,"chargers":1,"totalChargers":2,"chargerCounts":{"slow":0,"fast":0,"ultraFast":1,"hyperFast":1},"operator":"브라이트에너지파트너스","useTime":"24시간 이용가능","parkingFree":"Y","kind":"C0","kindDetail":"C001"},{"id":"BE241244","name":"워터 영산휴게소 창원방향","address":"경상남도 창녕군 영산면 장척호수길 56-110","lat":35.429259,"lng":128.495536,"power":350,"chargers":1,"totalChargers":2,"chargerCounts":{"slow":0,"fast":0,"ultraFast":1,"hyperFast":1},"operator":"브라이트에너지파트너스","useTime":"24시간 이용가능","parkingFree":"Y","kind":"C0","kindDetail":"C001"},{"id":"BE241233","name":"워터 영천휴게소 대구방향","address":"경상북도 영천시 임고면 운주로 791","lat":36.0531593,"lng":129.0454953,"power":350,"chargers":7,"totalChargers":8,"chargerCounts":{"slow":0,"fast":0,"ultraFast":1,"hyperFast":7},"operator":"브라이트에너지파트너스","useTime":"24시간 이용가능","parkingFree":"Y","kind":"C0","kindDetail":"C001"},{"id":"BE241214","name":"워터 옥계휴게소 속초방향","address":"강원특별자치도 강릉시 옥계면 동해고속도로 320","lat":37.6151004,"lng":129.0608237,"power":350,"chargers":2,"totalChargers":3,"chargerCounts":{"slow":0,"fast":0,"ultraFast":1,"hyperFast":2},"operator":"브라이트에너지파트너스","useTime":"24시간 이용가능","parkingFree":"Y","kind":"C0","kindDetail":"C001"},{"id":"BE241215","name":"워터 용인휴게소 강릉방향","address":"경기도 용인시 처인구 주북로94번길 30-1","lat":37.246149,"lng":127.241161,"power":350,"chargers":7,"totalChargers":8,"chargerCounts":{"slow":0,"fast":0,"ultraFast":1,"hyperFast":7},"operator":"브라이트에너지파트너스","useTime":"24시간 이용가능","parkingFree":"Y","kind":"C0","kindDetail":"C001"},{"id":"BE241216","name":"워터 용인휴게소 인천방향","address":"경기도 용인시 처인구 주북로 66-14","lat":37.2478822,"lng":127.2388871,"power":350,"chargers":1,"totalChargers":2,"chargerCounts":{"slow":0,"fast":0,"ultraFast":1,"hyperFast":1},"operator":"브라이트에너지파트너스","useTime":"24시간 이용가능","parkingFree":"Y","kind":"C0","kindDetail":"C001"},{"id":"BE241217","name":"워터 원주휴게소 춘천방향","address":"강원특별자치도 원주시 호저면 마근거리길 110","lat":37.4345878,"lng":127.9316612,"power":350,"chargers":4,"totalChargers":5,"chargerCounts":{"slow":0,"fast":0,"ultraFast":1,"hyperFast":4},"operator":"브라이트에너지파트너스","useTime":"24시간 이용가능","parkingFree":"Y","kind":"C0","kindDetail":"C001"},{"id":"BE241234","name":"워터 의성휴게소 청주방향","address":"경상북도 의성군 안계면 새못안길 45-49","lat":36.4108117,"lng":128.4450437,"power":350,"chargers":1,"totalChargers":2,"chargerCounts":{"slow":0,"fast":0,"ultraFast":1,"hyperFast":1},"operator":"브라이트에너지파트너스","useTime":"24시간 이용가능","parkingFree":"Y","kind":"C0","kindDetail":"C001"},{"id":"BE241227","name":"워터 천등산휴게소 제천방향","address":"충청북도 충주시 산척면 평택제천고속도로 106","lat":37.0617226,"lng":127.9394679,"power":350,"chargers":2,"totalChargers":3,"chargerCounts":{"slow":0,"fast":0,"ultraFast":1,"hyperFast":2},"operator":"브라이트에너지파트너스","useTime":"24시간 이용가능","parkingFree":"Y","kind":"C0","kindDetail":"C001"},{"id":"BE241228","name":"워터 천등산휴게소 평택방향","address":"충청북도 충주시 산척면 평택제천고속도로 109","lat":37.0764685,"lng":127.9883919,"power":350,"chargers":2,"totalChargers":3,"chargerCounts":{"slow":0,"fast":0,"ultraFast":1,"hyperFast":2},"operator":"브라이트에너지파트너스","useTime":"24시간 이용가능","parkingFree":"Y","kind":"C0","kindDetail":"C001"},{"id":"BE241235","name":"워터 청통휴게소 대구방향","address":"경상북도 영천시 청통면 청통로 334-42","lat":35.9944665,"lng":128.8600402,"power":350,"chargers":4,"totalChargers":5,"chargerCounts":{"slow":0,"fast":0,"ultraFast":1,"hyperFast":4},"operator":"브라이트에너지파트너스","useTime":"24시간 이용가능","parkingFree":"Y","kind":"C0","kindDetail":"C001"},{"id":"BE241229","name":"워터 충주휴게소 양평방향","address":"충청북도 충주시 중앙탑면 중부내륙고속도로 230","lat":37.0234561,"lng":127.839258,"power":350,"chargers":6,"totalChargers":7,"chargerCounts":{"slow":0,"fast":0,"ultraFast":1,"hyperFast":6},"operator":"브라이트에너지파트너스","useTime":"24시간 이용가능","parkingFree":"Y","kind":"C0","kindDetail":"C001"},{"id":"BE241236","name":"워터 칠곡휴게소 서울방향","address":"경상북도 칠곡군 왜관읍 경부고속도로 158","lat":36.012093,"lng":128.4305681,"power":350,"chargers":2,"totalChargers":3,"chargerCounts":{"slow":0,"fast":0,"ultraFast":1,"hyperFast":2},"operator":"브라이트에너지파트너스","useTime":"24시간 이용가능","parkingFree":"Y","kind":"C0","kindDetail":"C001"},{"id":"BE241218","name":"워터 평창휴게소 강릉방향","address":"강원특별자치도 평창군 용평면 경강로 2159-58","lat":37.6056518,"lng":128.4526894,"power":350,"chargers":7,"totalChargers":8,"chargerCounts":{"slow":0,"fast":0,"ultraFast":1,"hyperFast":7},"operator":"브라이트에너지파트너스","useTime":"24시간 이용가능","parkingFree":"Y","kind":"C0","kindDetail":"C001"},{"id":"BE241248","name":"워터 함안휴게소 부산방향","address":"경상남도 함안군 군북면 현포로 205","lat":35.293782,"lng":128.347778,"power":350,"chargers":4,"totalChargers":5,"chargerCounts":{"slow":0,"fast":0,"ultraFast":1,"hyperFast":4},"operator":"브라이트에너지파트너스","useTime":"24시간 이용가능","parkingFree":"Y","kind":"C0","kindDetail":"C001"},{"id":"BE241249","name":"워터 함안휴게소 순천방향","address":"경상남도 함안군 군북면 현포로 205-1","lat":35.294895,"lng":128.343693,"power":350,"chargers":6,"totalChargers":7,"chargerCounts":{"slow":0,"fast":0,"ultraFast":1,"hyperFast":6},"operator":"브라이트에너지파트너스","useTime":"24시간 이용가능","parkingFree":"Y","kind":"C0","kindDetail":"C001"},{"id":"BE241250","name":"워터 현풍휴게소 대구방향","address":"대구광역시 달성군 현풍읍 비슬로 741","lat":35.702207,"lng":128.437991,"power":350,"chargers":1,"totalChargers":2,"chargerCounts":{"slow":0,"fast":0,"ultraFast":1,"hyperFast":1},"operator":"브라이트에너지파트너스","useTime":"24시간 이용가능","parkingFree":"Y","kind":"C0","kindDetail":"C001"},{"id":"BE241251","name":"워터 현풍휴게소 창원방향","address":"대구광역시 달성군 현풍읍 성하길 48","lat":35.70169,"lng":128.435728,"power":350,"chargers":1,"totalChargers":2,"chargerCounts":{"slow":0,"fast":0,"ultraFast":1,"hyperFast":1},"operator":"브라이트에너지파트너스","useTime":"24시간 이용가능","parkingFree":"Y","kind":"C0","kindDetail":"C001"},{"id":"BE241221","name":"워터 홍천강휴게소 춘천방향","address":"강원특별자치도 홍천군 북방면 도사곡길 223","lat":37.7129251,"lng":127.8278683,"power":350,"chargers":2,"totalChargers":3,"chargerCounts":{"slow":0,"fast":0,"ultraFast":1,"hyperFast":2},"operator":"브라이트에너지파트너스","useTime":"24시간 이용가능","parkingFree":"Y","kind":"C0","kindDetail":"C001"},{"id":"BE241219","name":"워터 홍천휴게소 서울방향","address":"강원특별자치도 홍천군 화촌면 서울양양고속도로 83","lat":37.7590699,"lng":128.0058741,"power":350,"chargers":3,"totalChargers":4,"chargerCounts":{"slow":0,"fast":0,"ultraFast":1,"hyperFast":3},"operator":"브라이트에너지파트너스","useTime":"24시간 이용가능","parkingFree":"Y","kind":"C0","kindDetail":"C001"},{"id":"BE241220","name":"워터 홍천휴게소 양양방향","address":"강원특별자치도 홍천군 화촌면 서울양양고속도로 84","lat":37.7573166,"lng":128.0043779,"power":350,"chargers":1,"totalChargers":2,"chargerCounts":{"slow":0,"fast":0,"ultraFast":1,"hyperFast":1},"operator":"브라이트에너지파트너스","useTime":"24시간 이용가능","parkingFree":"Y","kind":"C0","kindDetail":"C001"},{"id":"BE241222","name":"워터 횡성휴게소 강릉방향","address":"강원특별자치도 횡성군 안흥면 영동고속도로 154-1","lat":37.4633333,"lng":128.1345784,"power":350,"chargers":5,"totalChargers":6,"chargerCounts":{"slow":0,"fast":0,"ultraFast":1,"hyperFast":5},"operator":"브라이트에너지파트너스","useTime":"24시간 이용가능","parkingFree":"Y","kind":"C0","kindDetail":"C001"},{"id":"ST411501","name":"의정부휴게소","address":"경기도 의정부시 구리포천고속도로 19","lat":37.73183,"lng":127.115003,"power":350,"chargers":2,"totalChargers":12,"chargerCounts":{"slow":0,"fast":8,"ultraFast":2,"hyperFast":2},"operator":"SK일렉링크","useTime":"24시간 이용가능","parkingFree":"Y","kind":"C0","kindDetail":"C001"},{"id":"ST601538","name":"이서휴게소 (순천)","address":"전북특별자치도 완주군 이서면 호남고속도로 161-1","lat":35.803204084,"lng":127.02411016,"power":350,"chargers":6,"totalChargers":7,"chargerCounts":{"slow":0,"fast":1,"ultraFast":0,"hyperFast":6},"operator":"SK일렉링크","useTime":"24시간 이용가능","parkingFree":"Y","kind":"C0","kindDetail":"C001"},{"id":"ST601539","name":"이서휴게소 (천안)","address":"전북특별자치도 완주군 이서면 호남고속도로 162","lat":35.801385513,"lng":127.02542891,"power":350,"chargers":5,"totalChargers":6,"chargerCounts":{"slow":0,"fast":1,"ultraFast":0,"hyperFast":5},"operator":"SK일렉링크","useTime":"24시간 이용가능","parkingFree":"Y","kind":"C0","kindDetail":"C001"},{"id":"SGMAC058","name":"이천쌀휴게소(국도부)","address":"경기도 이천시 신둔면 용면리 산 77-1","lat":37.2939384,"lng":127.3793952,"power":350,"chargers":3,"totalChargers":3,"chargerCounts":{"slow":0,"fast":0,"ultraFast":0,"hyperFast":3},"operator":"SK시그넷","useTime":"24시간 이용가능","parkingFree":"Y","kind":"C0","kindDetail":"C001"},{"id":"SGMAC015","name":"이천쌀휴게소(하남)","address":"경기도 이천시 신둔면 서이천로853번길 346-129","lat":37.293131,"lng":127.37901,"power":350,"chargers":4,"totalChargers":4,"chargerCounts":{"slow":0,"fast":0,"ultraFast":0,"hyperFast":4},"operator":"SK시그넷","useTime":"24시간 이용가능","parkingFree":"Y","kind":"C0","kindDetail":"C001"},{"id":"ST415015","name":"이천휴게소 (하남)","address":"경기도 이천시 신둔면 서이천로853번길 346-129","lat":37.2938975,"lng":127.3795359,"power":350,"chargers":1,"totalChargers":4,"chargerCounts":{"slow":0,"fast":0,"ultraFast":3,"hyperFast":1},"operator":"SK일렉링크","useTime":"24시간 이용가능","parkingFree":"Y","kind":"C0","kindDetail":"C001"},{"id":"EC450033","name":"익산미륵사지(천안)휴게소 (급)","address":"전북특별자치도 익산시 여산면 호남고속도로 192","lat":36.049,"lng":127.1048,"power":350,"chargers":4,"totalChargers":4,"chargerCounts":{"slow":0,"fast":0,"ultraFast":0,"hyperFast":4},"operator":"이지차저","useTime":"24시간 이용가능","parkingFree":"Y","kind":"C0","kindDetail":"C001"},{"id":"KL200101","name":"인계동 만땅 충전소","address":"경기도 수원시 팔달구 권광로180번길 49","lat":37.263067535,"lng":127.03549081,"power":350,"chargers":2,"totalChargers":12,"chargerCounts":{"slow":0,"fast":2,"ultraFast":8,"hyperFast":2},"operator":"클린일렉스","useTime":"24시간 이용가능","parkingFree":"Y","kind":"G0","kindDetail":"G004"},{"id":"ST441325","name":"입장휴게소 (서울)","address":"충청남도 천안시 서북구 입장면 연곡길 407","lat":36.943187633,"lng":127.19017427,"power":350,"chargers":1,"totalChargers":3,"chargerCounts":{"slow":0,"fast":0,"ultraFast":2,"hyperFast":1},"operator":"SK일렉링크","useTime":"24시간 이용가능","parkingFree":"Y","kind":"C0","kindDetail":"C001"},{"id":"CV002143","name":"장사해수욕장","address":"경상북도 영덕군 남정면 동해대로 3592","lat":36.2817726,"lng":129.3746735,"power":350,"chargers":2,"totalChargers":5,"chargerCounts":{"slow":0,"fast":3,"ultraFast":0,"hyperFast":2},"operator":"채비","useTime":"24시간 이용가능","parkingFree":"Y","kind":"D0","kindDetail":"D007"},{"id":"ME21A914","name":"장흥정남진 휴게소","address":"전남광주통합특별시 장흥군 부산면 호계리 산215-2","lat":34.7209284,"lng":126.9293707,"power":350,"chargers":2,"totalChargers":4,"chargerCounts":{"slow":0,"fast":2,"ultraFast":0,"hyperFast":2},"operator":"기후에너지환경부","useTime":"24시간 이용가능","parkingFree":"Y","kind":"C0","kindDetail":"C001"},{"id":"SGMAC025","name":"장흥정남진휴게소(목포)","address":"전남광주통합특별시 장흥군 부산면 남해고속도로 41","lat":34.720311,"lng":126.930931,"power":350,"chargers":2,"totalChargers":3,"chargerCounts":{"slow":0,"fast":0,"ultraFast":1,"hyperFast":2},"operator":"SK시그넷","useTime":"24시간 이용가능","parkingFree":"Y","kind":"C0","kindDetail":"C001"},{"id":"CV001675","name":"정왕동 공영주차장","address":"경상남도 진주시 소호로 113","lat":35.1787247,"lng":128.1351203,"power":350,"chargers":2,"totalChargers":2,"chargerCounts":{"slow":0,"fast":0,"ultraFast":0,"hyperFast":2},"operator":"채비","useTime":"09:00~18:00","parkingFree":"Y","kind":"G0","kindDetail":"G004"},{"id":"SGMAC041","name":"주암휴게소(순천)","address":"전남광주통합특별시 순천시 주암면 호남고속도로 23","lat":35.075958,"lng":127.264313,"power":350,"chargers":4,"totalChargers":4,"chargerCounts":{"slow":0,"fast":0,"ultraFast":0,"hyperFast":4},"operator":"SK시그넷","useTime":"24시간 이용가능","parkingFree":"Y","kind":"C0","kindDetail":"C001"},{"id":"SGMAC032","name":"주암휴게소(천안)","address":"전남광주통합특별시 순천시 주암면 호남고속도로 24","lat":35.0762,"lng":127.265671,"power":350,"chargers":2,"totalChargers":3,"chargerCounts":{"slow":0,"fast":0,"ultraFast":1,"hyperFast":2},"operator":"SK시그넷","useTime":"24시간 이용가능","parkingFree":"Y","kind":"C0","kindDetail":"C001"},{"id":"ST431146","name":"죽암휴게소 (부산)","address":"충청북도 청주시 서원구 현도면 경부고속도로 289","lat":36.4869665,"lng":127.4291915,"power":350,"chargers":1,"totalChargers":5,"chargerCounts":{"slow":0,"fast":0,"ultraFast":4,"hyperFast":1},"operator":"SK일렉링크","useTime":"24시간 이용가능","parkingFree":"Y","kind":"C0","kindDetail":"C001"},{"id":"ME20D901","name":"죽전(서울) 휴게소","address":"경기도 용인시 수지구 경부고속도로400","lat":37.3316793,"lng":127.1045386,"power":350,"chargers":2,"totalChargers":4,"chargerCounts":{"slow":0,"fast":2,"ultraFast":0,"hyperFast":2},"operator":"기후에너지환경부","useTime":"24시간 이용가능","parkingFree":"Y","kind":"C0","kindDetail":"C001"},{"id":"SGMAC023","name":"죽전휴게소(서울)","address":"경기도 용인시 수지구 경부고속도로 400","lat":37.331727,"lng":127.104437,"power":350,"chargers":4,"totalChargers":4,"chargerCounts":{"slow":0,"fast":0,"ultraFast":0,"hyperFast":4},"operator":"SK시그넷","useTime":"24시간 이용가능","parkingFree":"Y","kind":"C0","kindDetail":"C001"},{"id":"SGMAC036","name":"지리산휴게소(광주)","address":"전북특별자치도 남원시 아영면 광주대구고속도로 75","lat":35.483588,"lng":127.568012,"power":350,"chargers":4,"totalChargers":4,"chargerCounts":{"slow":0,"fast":0,"ultraFast":0,"hyperFast":4},"operator":"SK시그넷","useTime":"24시간 이용가능","parkingFree":"Y","kind":"C0","kindDetail":"C001"},{"id":"SGMAC043","name":"지리산휴게소(대구)","address":"전북특별자치도 남원시 아영면 광주대구고속도로 76-1","lat":35.480898,"lng":127.566183,"power":350,"chargers":2,"totalChargers":2,"chargerCounts":{"slow":0,"fast":0,"ultraFast":0,"hyperFast":2},"operator":"SK시그넷","useTime":"24시간 이용가능","parkingFree":"Y","kind":"C0","kindDetail":"C001"},{"id":"ST481713","name":"진주휴게소 (부산)","address":"경상남도 진주시 남해고속도로 194","lat":35.159693446,"lng":128.12198579,"power":350,"chargers":1,"totalChargers":5,"chargerCounts":{"slow":0,"fast":0,"ultraFast":4,"hyperFast":1},"operator":"SK일렉링크","useTime":"24시간 이용가능","parkingFree":"Y","kind":"C0","kindDetail":"C001"},{"id":"CV001364","name":"채비스테이 강남서초센터","address":"서울특별시 서초구 남부순환로 2463","lat":37.482766,"lng":127.019869,"power":350,"chargers":1,"totalChargers":8,"chargerCounts":{"slow":0,"fast":4,"ultraFast":3,"hyperFast":1},"operator":"채비","useTime":"24시간 이용가능","parkingFree":"Y","kind":"E0","kindDetail":"E005"},{"id":"CV000849","name":"채비초급속충전소1","address":"대구광역시 달성군 유가읍 테크노순환로8길 8","lat":35.6800927,"lng":128.4660623,"power":400,"chargers":1,"totalChargers":6,"chargerCounts":{"slow":0,"fast":0,"ultraFast":5,"hyperFast":1},"operator":"채비","useTime":"24시간 이용가능(입구 24시간 개방)","parkingFree":"Y","kind":"B0","kindDetail":"B004"},{"id":"CV001630","name":"천우모빌리티 제주","address":"제주특별자치도 제주시 연삼로 759","lat":33.5118762,"lng":126.5670278,"power":350,"chargers":1,"totalChargers":9,"chargerCounts":{"slow":0,"fast":8,"ultraFast":0,"hyperFast":1},"operator":"채비","useTime":"24시간 이용가능","parkingFree":"Y","kind":"E0","kindDetail":"E001"},{"id":"ST477502","name":"청송휴게소 (영덕)","address":"경상북도 청송군 파천면 중평병부길 203-115","lat":36.4555278,"lng":129.0130349,"power":350,"chargers":1,"totalChargers":4,"chargerCounts":{"slow":0,"fast":0,"ultraFast":3,"hyperFast":1},"operator":"SK일렉링크","useTime":"24시간 이용가능","parkingFree":"Y","kind":"C0","kindDetail":"C001"},{"id":"ME21A902","name":"추풍령(부산) 휴게소","address":"경상북도 김천시 봉산면 경부고속도로 213","lat":36.2000503,"lng":128.0007836,"power":350,"chargers":2,"totalChargers":4,"chargerCounts":{"slow":0,"fast":2,"ultraFast":0,"hyperFast":2},"operator":"기후에너지환경부","useTime":"24시간 이용가능","parkingFree":"Y","kind":"C0","kindDetail":"C001"},{"id":"EC470016","name":"추풍령(부산)휴게소 (급)","address":"경상북도 김천시 봉산면 경부고속도로 214-1","lat":36.199932368,"lng":128.00358508,"power":360,"chargers":4,"totalChargers":4,"chargerCounts":{"slow":0,"fast":0,"ultraFast":0,"hyperFast":4},"operator":"이지차저","useTime":"24시간 이용가능","parkingFree":"Y","kind":"C0","kindDetail":"C001"},{"id":"ME21A901","name":"추풍령(서울) 휴게소","address":"경상북도 김천시 봉산면 경부고속도로 214-1","lat":36.2003533,"lng":128.0031953,"power":350,"chargers":2,"totalChargers":4,"chargerCounts":{"slow":0,"fast":2,"ultraFast":0,"hyperFast":2},"operator":"기후에너지환경부","useTime":"24시간 이용가능","parkingFree":"Y","kind":"C0","kindDetail":"C001"},{"id":"EC470014","name":"추풍령(서울)휴게소 (급)","address":"경상북도 김천시 봉산면 경부고속도로 214-1","lat":36.199932368,"lng":128.00358508,"power":360,"chargers":4,"totalChargers":4,"chargerCounts":{"slow":0,"fast":0,"ultraFast":0,"hyperFast":4},"operator":"이지차저","useTime":"24시간 이용가능","parkingFree":"Y","kind":"C0","kindDetail":"C001"},{"id":"CV004577","name":"추풍령휴게소(부산방향)","address":"경상북도 김천시 봉산면 경부고속도로 213-1","lat":36.2015123,"lng":128.0004282,"power":350,"chargers":2,"totalChargers":7,"chargerCounts":{"slow":0,"fast":1,"ultraFast":4,"hyperFast":2},"operator":"채비","useTime":"24시간 이용가능","parkingFree":"Y","kind":"C0","kindDetail":"C001"},{"id":"EC450030","name":"춘향휴게소 (순천방향) (급)","address":"전북특별자치도 남원시 수지면 순천완주고속도로 49","lat":35.3365467,"lng":127.3516,"power":350,"chargers":2,"totalChargers":2,"chargerCounts":{"slow":0,"fast":0,"ultraFast":0,"hyperFast":2},"operator":"이지차저","useTime":"24시간 이용가능","parkingFree":"Y","kind":"C0","kindDetail":"C001"},{"id":"EC450032","name":"춘향휴게소 (완주방향) (급)","address":"전북특별자치도 남원시 수지면 순천완주고속도로 50","lat":35.3377,"lng":127.3538,"power":350,"chargers":2,"totalChargers":2,"chargerCounts":{"slow":0,"fast":0,"ultraFast":0,"hyperFast":2},"operator":"이지차저","useTime":"24시간 이용가능","parkingFree":"Y","kind":"C0","kindDetail":"C001"},{"id":"CV004732","name":"춘향휴게소(순천방향)","address":"전북특별자치도 남원시 수지면 순천완주고속도로 49","lat":35.3370177,"lng":127.351629,"power":350,"chargers":3,"totalChargers":4,"chargerCounts":{"slow":0,"fast":1,"ultraFast":0,"hyperFast":3},"operator":"채비","useTime":"24시간 이용가능","parkingFree":"Y","kind":"C0","kindDetail":"C001"},{"id":"CV004731","name":"춘향휴게소(완주방향)","address":"전북특별자치도 남원시 수지면 순천완주고속도로 50","lat":35.3377397,"lng":127.353813,"power":350,"chargers":3,"totalChargers":4,"chargerCounts":{"slow":0,"fast":1,"ultraFast":0,"hyperFast":3},"operator":"채비","useTime":"24시간 이용가능","parkingFree":"Y","kind":"C0","kindDetail":"C001"},{"id":"ME21A907","name":"충주(양평) 휴게소","address":"충청북도 충주시 중앙탑면 중부내륙고속도로 230","lat":37.0228414,"lng":127.8389125,"power":350,"chargers":2,"totalChargers":4,"chargerCounts":{"slow":0,"fast":2,"ultraFast":0,"hyperFast":2},"operator":"기후에너지환경부","useTime":"24시간 이용가능","parkingFree":"Y","kind":"C0","kindDetail":"C001"},{"id":"ME21A908","name":"치악(춘천) 휴게소","address":"강원특별자치도 원주시 신림면 다리실2길 32","lat":37.2561655,"lng":128.0494154,"power":350,"chargers":2,"totalChargers":4,"chargerCounts":{"slow":0,"fast":2,"ultraFast":0,"hyperFast":2},"operator":"기후에너지환경부","useTime":"24시간 이용가능","parkingFree":"Y","kind":"C0","kindDetail":"C001"},{"id":"CV004584","name":"칠곡휴게소(부산방향)","address":"경상북도 칠곡군 석적읍 경부고속도로 159","lat":36.0205425,"lng":128.4284661,"power":350,"chargers":2,"totalChargers":9,"chargerCounts":{"slow":0,"fast":1,"ultraFast":6,"hyperFast":2},"operator":"채비","useTime":"24시간 이용가능","parkingFree":"Y","kind":"C0","kindDetail":"C001"},{"id":"CV004560","name":"칠서휴게소(양평방향)","address":"경상남도 함안군 칠서면 계내리 38,1356-4","lat":35.3702961,"lng":128.4972354,"power":350,"chargers":1,"totalChargers":4,"chargerCounts":{"slow":0,"fast":0,"ultraFast":3,"hyperFast":1},"operator":"채비","useTime":"24시간 이용가능","parkingFree":"Y","kind":"C0","kindDetail":"C001"},{"id":"ST600528","name":"코레일 광명역(A환승주차장)","address":"경기도 광명시 덕안로 16","lat":37.4194648,"lng":126.8852467,"power":350,"chargers":1,"totalChargers":20,"chargerCounts":{"slow":15,"fast":0,"ultraFast":4,"hyperFast":1},"operator":"SK일렉링크","useTime":"24시간 이용가능","parkingFree":"N","kind":"B0","kindDetail":"B003"},{"id":"ST600530","name":"코레일 부산역","address":"부산광역시 동구 중앙대로 210","lat":35.1159254,"lng":129.0421003,"power":350,"chargers":1,"totalChargers":6,"chargerCounts":{"slow":0,"fast":1,"ultraFast":4,"hyperFast":1},"operator":"SK일렉링크","useTime":"24시간 이용가능","parkingFree":"Y","kind":"B0","kindDetail":"B004"},{"id":"EC480012","name":"통도사(부산)휴게소 (급)","address":"경상남도 양산시 하북면 경부고속도로 31-1","lat":35.490075236,"lng":129.09204145,"power":360,"chargers":4,"totalChargers":4,"chargerCounts":{"slow":0,"fast":0,"ultraFast":0,"hyperFast":4},"operator":"이지차저","useTime":"24시간 이용가능","parkingFree":"Y","kind":"C0","kindDetail":"C001"},{"id":"CV004566","name":"평사휴게소(부산방향)","address":"경상북도 경산시 진량읍 경부고속도로 105","lat":35.8851745,"lng":128.8653968,"power":350,"chargers":2,"totalChargers":5,"chargerCounts":{"slow":0,"fast":0,"ultraFast":3,"hyperFast":2},"operator":"채비","useTime":"24시간 이용가능","parkingFree":"Y","kind":"C0","kindDetail":"C001"},{"id":"CV002099","name":"한국뇌연구원 제1주차장","address":"대구광역시 동구 첨단로 61","lat":35.881813,"lng":128.7293279,"power":350,"chargers":2,"totalChargers":3,"chargerCounts":{"slow":0,"fast":1,"ultraFast":0,"hyperFast":2},"operator":"채비","useTime":"24시간 이용가능","parkingFree":"Y","kind":"A0","kindDetail":"A003"},{"id":"CV004121","name":"한밭종합운동장","address":"대전광역시 중구 대종로 373","lat":36.317331,"lng":127.42801,"power":350,"chargers":2,"totalChargers":14,"chargerCounts":{"slow":8,"fast":4,"ultraFast":0,"hyperFast":2},"operator":"채비","useTime":"24시간 이용가능","parkingFree":"Y","kind":"J0","kindDetail":"J007"},{"id":"HJ000452","name":"한진부산컨테이너터미널","address":"경상남도 창원시 진해구 신항로 433","lat":35.0808757,"lng":128.784622,"power":360,"chargers":2,"totalChargers":12,"chargerCounts":{"slow":0,"fast":0,"ultraFast":10,"hyperFast":2},"operator":"㈜한진","useTime":"24시간 이용가능","parkingFree":"Y","kind":"G0","kindDetail":"G004"},{"id":"ST468601","name":"함평나비휴게소 (광주)","address":"전남광주통합특별시 함평군 엄다면 무안광주고속도로 12","lat":35.0371304,"lng":126.509247,"power":350,"chargers":1,"totalChargers":2,"chargerCounts":{"slow":0,"fast":0,"ultraFast":1,"hyperFast":1},"operator":"SK일렉링크","useTime":"24시간 이용가능","parkingFree":"Y","kind":"C0","kindDetail":"C001"},{"id":"SGMAC033","name":"함평나비휴게소(광주)","address":"전남광주통합특별시 함평군 엄다면 무안광주고속도로 12","lat":35.037635,"lng":126.512286,"power":350,"chargers":5,"totalChargers":6,"chargerCounts":{"slow":0,"fast":0,"ultraFast":1,"hyperFast":5},"operator":"SK시그넷","useTime":"24시간 이용가능","parkingFree":"Y","kind":"C0","kindDetail":"C001"},{"id":"SGMAC029","name":"함평천지휴게소(목포)","address":"전남광주통합특별시 함평군 함평읍 서해안고속도로 31","lat":35.068764,"lng":126.478367,"power":350,"chargers":4,"totalChargers":4,"chargerCounts":{"slow":0,"fast":0,"ultraFast":0,"hyperFast":4},"operator":"SK시그넷","useTime":"24시간 이용가능","parkingFree":"Y","kind":"C0","kindDetail":"C001"},{"id":"CV004574","name":"함평천지휴게소(서울방향)","address":"전남광주통합특별시 함평군 손불면 서해안고속도로 38","lat":35.1313441,"lng":126.4820481,"power":350,"chargers":2,"totalChargers":5,"chargerCounts":{"slow":0,"fast":0,"ultraFast":3,"hyperFast":2},"operator":"채비","useTime":"24시간 이용가능","parkingFree":"Y","kind":"C0","kindDetail":"C001"},{"id":"CV002115","name":"혁신도시 공영주차장","address":"대구광역시 동구 신서동 1152-2","lat":35.878997744,"lng":128.73511421,"power":350,"chargers":2,"totalChargers":4,"chargerCounts":{"slow":0,"fast":2,"ultraFast":0,"hyperFast":2},"operator":"채비","useTime":"24시간 이용가능","parkingFree":"N","kind":"B0","kindDetail":"B001"},{"id":"ST448004","name":"홍성휴게소 (서울)","address":"충청남도 홍성군 은하면 서해안고속도로 220","lat":36.5510131,"lng":126.5812846,"power":350,"chargers":1,"totalChargers":2,"chargerCounts":{"slow":0,"fast":0,"ultraFast":1,"hyperFast":1},"operator":"SK일렉링크","useTime":"24시간 이용가능","parkingFree":"Y","kind":"C0","kindDetail":"C001"},{"id":"SGMAC052","name":"홍성휴게소(서울)","address":"충청남도 홍성군 은하면 서해안고속도로 220","lat":36.55373,"lng":126.581783,"power":350,"chargers":7,"totalChargers":8,"chargerCounts":{"slow":0,"fast":0,"ultraFast":1,"hyperFast":7},"operator":"SK시그넷","useTime":"24시간 이용가능","parkingFree":"Y","kind":"C0","kindDetail":"C001"},{"id":"ST427204","name":"홍천강휴게소 (춘천)","address":"강원특별자치도 홍천군 북방면 도사곡길 223","lat":37.713293,"lng":127.8259105,"power":350,"chargers":1,"totalChargers":2,"chargerCounts":{"slow":0,"fast":0,"ultraFast":1,"hyperFast":1},"operator":"SK일렉링크","useTime":"24시간 이용가능","parkingFree":"Y","kind":"C0","kindDetail":"C001"},{"id":"ST427203","name":"홍천휴게소 (서울)","address":"강원특별자치도 홍천군 화촌면 서울양양고속도로 83","lat":37.75898851,"lng":128.0064814,"power":350,"chargers":1,"totalChargers":3,"chargerCounts":{"slow":0,"fast":0,"ultraFast":2,"hyperFast":1},"operator":"SK일렉링크","useTime":"24시간 이용가능","parkingFree":"Y","kind":"C0","kindDetail":"C001"},{"id":"SGMAC051","name":"화성휴게소(목포)","address":"경기도 화성시 만세구 팔탄면 서해안고속도로 301","lat":37.146054,"lng":126.878832,"power":350,"chargers":4,"totalChargers":4,"chargerCounts":{"slow":0,"fast":0,"ultraFast":0,"hyperFast":4},"operator":"SK시그넷","useTime":"24시간 이용가능","parkingFree":"Y","kind":"C0","kindDetail":"C001"},{"id":"SGMAC022","name":"황간휴게소(부산)","address":"충청북도 영동군 황간면 회포길 102","lat":36.249618,"lng":127.852841,"power":350,"chargers":5,"totalChargers":5,"chargerCounts":{"slow":0,"fast":0,"ultraFast":0,"hyperFast":5},"operator":"SK시그넷","useTime":"24시간 이용가능","parkingFree":"Y","kind":"C0","kindDetail":"C001"},{"id":"ST461507","name":"황전휴게소 (순천)","address":"전남광주통합특별시 순천시 황전면 순천완주고속도로 25","lat":35.148837593,"lng":127.45416816,"power":350,"chargers":1,"totalChargers":3,"chargerCounts":{"slow":0,"fast":0,"ultraFast":2,"hyperFast":1},"operator":"SK일렉링크","useTime":"24시간 이용가능","parkingFree":"Y","kind":"C0","kindDetail":"C001"},{"id":"ST461506","name":"황전휴게소 (전주)","address":"전남광주통합특별시 순천시 황전면 순천완주고속도로 28","lat":35.1532275,"lng":127.454421,"power":350,"chargers":1,"totalChargers":2,"chargerCounts":{"slow":0,"fast":0,"ultraFast":1,"hyperFast":1},"operator":"SK일렉링크","useTime":"24시간 이용가능","parkingFree":"Y","kind":"C0","kindDetail":"C001"},{"id":"SGMAC020","name":"황전휴게소(순천)","address":"전남광주통합특별시 순천시 황전면 순천완주고속도로 25","lat":35.148335,"lng":127.454695,"power":350,"chargers":2,"totalChargers":2,"chargerCounts":{"slow":0,"fast":0,"ultraFast":0,"hyperFast":2},"operator":"SK시그넷","useTime":"24시간 이용가능","parkingFree":"Y","kind":"C0","kindDetail":"C001"},{"id":"SGMAC050","name":"황전휴게소(완주)","address":"전남광주통합특별시 순천시 황전면 순천완주고속도로 28","lat":35.15331603,"lng":127.4546436,"power":350,"chargers":2,"totalChargers":3,"chargerCounts":{"slow":0,"fast":0,"ultraFast":1,"hyperFast":2},"operator":"SK시그넷","useTime":"24시간 이용가능","parkingFree":"Y","kind":"C0","kindDetail":"C001"},{"id":"ST427303","name":"횡성휴게소 (인천)","address":"강원특별자치도 횡성군 안흥면 영동고속도로 153","lat":37.464944984,"lng":128.13545984,"power":350,"chargers":1,"totalChargers":4,"chargerCounts":{"slow":0,"fast":0,"ultraFast":3,"hyperFast":1},"operator":"SK일렉링크","useTime":"24시간 이용가능","parkingFree":"Y","kind":"C0","kindDetail":"C001"}]}